Workbook

Sheet G合計
B3: 日時 | C3: 曜日 | D3: 実績 | E3: 取り分 | F3: 粗利 | G3: 実績累計 | H3: 予算 | I3: 予算累計 | K3: 差異 | L3: 1日粗利単価
B4: ='【大井町】売上'!B4 -> 46054 | C4: ='【大井町】売上'!C4 -> 日 | D4: ='【大井町】売上'!D4+'【蒲田】売上'!D4+'【巣鴨】売上'!D4 -> 0 | E4: ='【大井町】売上'!E4+'【蒲田】売上'!E4+'【巣鴨】売上'!E4 -> 0 | F4: ='【大井町】売上'!F4+'【蒲田】売上'!F4+'【巣鴨】売上'!F4 -> 0 | G4: =SUM(D4) -> 0 | H4: ='【大井町】売上'!H4+'【蒲田】売上'!H4+'【巣鴨】売上'!H4 -> 140000 | I4: =H4 -> 140000 | J4: =G4/I4 -> 0 | K4: =G4-I4 -> -140000 | L4: =M4/1 -> 0 | M4: =F4 -> 0
B5: ='【大井町】売上'!B5 -> 46055 | C5: ='【大井町】売上'!C5 -> 月 | D5: ='【大井町】売上'!D5+'【蒲田】売上'!D5+'【巣鴨】売上'!D5 -> 156000 | E5: ='【大井町】売上'!E5+'【蒲田】売上'!E5+'【巣鴨】売上'!E5 -> 85500 | F5: ='【大井町】売上'!F5+'【蒲田】売上'!F5+'【巣鴨】売上'!F5 -> 70500 | G5: =SUM(D5+G4) -> 156000 | H5: ='【大井町】売上'!H5+'【蒲田】売上'!H5+'【巣鴨】売上'!H5 -> 220000 | I5: =H5+I4 -> 360000 | J5: =G5/I5 -> 0.43333333 | K5: =G5-I5 -> -204000 | L5: =M5/1 -> 70500 | M5: =F5+M4 -> 70500
B6: ='【大井町】売上'!B6 -> 46056 | C6: ='【大井町】売上'!C6 -> 火 | D6: ='【大井町】売上'!D6+'【蒲田】売上'!D6+'【巣鴨】売上'!D6 -> 224000 | E6: ='【大井町】売上'!E6+'【蒲田】売上'!E6+'【巣鴨】売上'!E6 -> 124000 | F6: ='【大井町】売上'!F6+'【蒲田】売上'!F6+'【巣鴨】売上'!F6 -> 100000 | G6: =SUM(D6+G5) -> 380000 | H6: ='【大井町】売上'!H6+'【蒲田】売上'!H6+'【巣鴨】売上'!H6 -> 220000 | I6: =H6+I5 -> 580000 | J6: =G6/I6 -> 0.65517241 | K6: =G6-I6 -> -200000 | L6: =M6/2 -> 85250 | M6: =F6+M5 -> 170500
B7: ='【大井町】売上'!B7 -> 46057 | C7: ='【大井町】売上'!C7 -> 水 | D7: ='【大井町】売上'!D7+'【蒲田】売上'!D7+'【巣鴨】売上'!D7 -> 207000 | E7: ='【大井町】売上'!E7+'【蒲田】売上'!E7+'【巣鴨】売上'!E7 -> 117500 | F7: ='【大井町】売上'!F7+'【蒲田】売上'!F7+'【巣鴨】売上'!F7 -> 89500 | G7: =SUM(D7+G6) -> 587000 | H7: ='【大井町】売上'!H7+'【蒲田】売上'!H7+'【巣鴨】売上'!H7 -> 220000 | I7: =H7+I6 -> 800000 | J7: =G7/I7 -> 0.73375 | K7: =G7-I7 -> -213000 | L7: =M7/3 -> 86666.667 | M7: =F7+M6 -> 260000
B8: ='【大井町】売上'!B8 -> 46058 | C8: ='【大井町】売上'!C8 -> 木 | D8: ='【大井町】売上'!D8+'【蒲田】売上'!D8+'【巣鴨】売上'!D8 -> 220000 | E8: ='【大井町】売上'!E8+'【蒲田】売上'!E8+'【巣鴨】売上'!E8 -> 127925 | F8: ='【大井町】売上'!F8+'【蒲田】売上'!F8+'【巣鴨】売上'!F8 -> 92075 | G8: =SUM(D8+G7) -> 807000 | H8: ='【大井町】売上'!H8+'【蒲田】売上'!H8+'【巣鴨】売上'!H8 -> 220000 | I8: =H8+I7 -> 1020000 | J8: =G8/I8 -> 0.79117647 | K8: =G8-I8 -> -213000 | L8: =M8/4 -> 88018.75 | M8: =F8+M7 -> 352075
B9: ='【大井町】売上'!B9 -> 46059 | C9: ='【大井町】売上'!C9 -> 金 | D9: ='【大井町】売上'!D9+'【蒲田】売上'!D9+'【巣鴨】売上'!D9 -> 216000 | E9: ='【大井町】売上'!E9+'【蒲田】売上'!E9+'【巣鴨】売上'!E9 -> 119099 | F9: ='【大井町】売上'!F9+'【蒲田】売上'!F9+'【巣鴨】売上'!F9 -> 96901 | G9: =SUM(D9+G8) -> 1023000 | H9: ='【大井町】売上'!H9+'【蒲田】売上'!H9+'【巣鴨】売上'!H9 -> 220000 | I9: =H9+I8 -> 1240000 | J9: =G9/I9 -> 0.825 | K9: =G9-I9 -> -217000 | L9: =M9/5 -> 89795.2 | M9: =F9+M8 -> 448976
B10: ='【大井町】売上'!B10 -> 46060 | C10: ='【大井町】売上'!C10 -> 土 | D10: ='【大井町】売上'!D10+'【蒲田】売上'!D10+'【巣鴨】売上'!D10 -> 262000 | E10: ='【大井町】売上'!E10+'【蒲田】売上'!E10+'【巣鴨】売上'!E10 -> 139947 | F10: ='【大井町】売上'!F10+'【蒲田】売上'!F10+'【巣鴨】売上'!F10 -> 122053 | G10: =SUM(D10+G9) -> 1285000 | H10: ='【大井町】売上'!H10+'【蒲田】売上'!H10+'【巣鴨】売上'!H10 -> 220000 | I10: =H10+I9 -> 1460000 | J10: =G10/I10 -> 0.88013699 | K10: =G10-I10 -> -175000 | L10: =M10/6 -> 95171.5 | M10: =F10+M9 -> 571029
B11: ='【大井町】売上'!B11 -> 46061 | C11: ='【大井町】売上'!C11 -> 日 | D11: ='【大井町】売上'!D11+'【蒲田】売上'!D11+'【巣鴨】売上'!D11 -> 227000 | E11: ='【大井町】売上'!E11+'【蒲田】売上'!E11+'【巣鴨】売上'!E11 -> 128500 | F11: ='【大井町】売上'!F11+'【蒲田】売上'!F11+'【巣鴨】売上'!F11 -> 98500 | G11: =SUM(D11+G10) -> 1512000 | H11: ='【大井町】売上'!H11+'【蒲田】売上'!H11+'【巣鴨】売上'!H11 -> 220000 | I11: =H11+I10 -> 1680000 | J11: =G11/I11 -> 0.9 | K11: =G11-I11 -> -168000 | L11: =M11/7 -> 95647 | M11: =F11+M10 -> 669529
B12: ='【大井町】売上'!B12 -> 46062 | C12: ='【大井町】売上'!C12 -> 月 | D12: ='【大井町】売上'!D12+'【蒲田】売上'!D12+'【巣鴨】売上'!D12 -> 225000 | E12: ='【大井町】売上'!E12+'【蒲田】売上'!E12+'【巣鴨】売上'!E12 -> 126000 | F12: ='【大井町】売上'!F12+'【蒲田】売上'!F12+'【巣鴨】売上'!F12 -> 99000 | G12: =SUM(D12+G11) -> 1737000 | H12: ='【大井町】売上'!H12+'【蒲田】売上'!H12+'【巣鴨】売上'!H12 -> 220000 | I12: =H12+I11 -> 1900000 | J12: =G12/I12 -> 0.91421053 | K12: =G12-I12 -> -163000 | L12: =M12/8 -> 96066.125 | M12: =F12+M11 -> 768529
B13: ='【大井町】売上'!B13 -> 46063 | C13: ='【大井町】売上'!C13 -> 火 | D13: ='【大井町】売上'!D13+'【蒲田】売上'!D13+'【巣鴨】売上'!D13 -> 273000 | E13: ='【大井町】売上'!E13+'【蒲田】売上'!E13+'【巣鴨】売上'!E13 -> 152500 | F13: ='【大井町】売上'!F13+'【蒲田】売上'!F13+'【巣鴨】売上'!F13 -> 120500 | G13: =SUM(D13+G12) -> 2010000 | H13: ='【大井町】売上'!H13+'【蒲田】売上'!H13+'【巣鴨】売上'!H13 -> 220000 | I13: =H13+I12 -> 2120000 | J13: =G13/I13 -> 0.94811321 | K13: =G13-I13 -> -110000 | L13: =M13/9 -> 98781 | M13: =F13+M12 -> 889029
B14: ='【大井町】売上'!B14 -> 46064 | C14: ='【大井町】売上'!C14 -> 水 | D14: ='【大井町】売上'!D14+'【蒲田】売上'!D14+'【巣鴨】売上'!D14 -> 171000 | E14: ='【大井町】売上'!E14+'【蒲田】売上'!E14+'【巣鴨】売上'!E14 -> 95000 | F14: ='【大井町】売上'!F14+'【蒲田】売上'!F14+'【巣鴨】売上'!F14 -> 76000 | G14: =SUM(D14+G13) -> 2181000 | H14: ='【大井町】売上'!H14+'【蒲田】売上'!H14+'【巣鴨】売上'!H14 -> 220000 | I14: =H14+I13 -> 2340000 | J14: =G14/I14 -> 0.93205128 | K14: =G14-I14 -> -159000 | L14: =M14/10 -> 96502.9 | M14: =F14+M13 -> 965029
B15: ='【大井町】売上'!B15 -> 46065 | C15: ='【大井町】売上'!C15 -> 木 | D15: ='【大井町】売上'!D15+'【蒲田】売上'!D15+'【巣鴨】売上'!D15 -> 225000 | E15: ='【大井町】売上'!E15+'【蒲田】売上'!E15+'【巣鴨】売上'!E15 -> 130347 | F15: ='【大井町】売上'!F15+'【蒲田】売上'!F15+'【巣鴨】売上'!F15 -> 94653 | G15: =SUM(D15+G14) -> 2406000 | H15: ='【大井町】売上'!H15+'【蒲田】売上'!H15+'【巣鴨】売上'!H15 -> 220000 | I15: =H15+I14 -> 2560000 | J15: =G15/I15 -> 0.93984375 | K15: =G15-I15 -> -154000 | L15: =M15/11 -> 96334.727 | M15: =F15+M14 -> 1059682
B16: ='【大井町】売上'!B16 -> 46066 | C16: ='【大井町】売上'!C16 -> 金 | D16: ='【大井町】売上'!D16+'【蒲田】売上'!D16+'【巣鴨】売上'!D16 -> 133000 | E16: ='【大井町】売上'!E16+'【蒲田】売上'!E16+'【巣鴨】売上'!E16 -> 73000 | F16: ='【大井町】売上'!F16+'【蒲田】売上'!F16+'【巣鴨】売上'!F16 -> 60000 | G16: =SUM(D16+G15) -> 2539000 | H16: ='【大井町】売上'!H16+'【蒲田】売上'!H16+'【巣鴨】売上'!H16 -> 220000 | I16: =H16+I15 -> 2780000 | J16: =G16/I16 -> 0.91330935 | K16: =G16-I16 -> -241000 | L16: =M16/12 -> 93306.833 | M16: =F16+M15 -> 1119682
B17: ='【大井町】売上'!B17 -> 46067 | C17: ='【大井町】売上'!C17 -> 土 | D17: ='【大井町】売上'!D17+'【蒲田】売上'!D17+'【巣鴨】売上'!D17 -> 152000 | E17: ='【大井町】売上'!E17+'【蒲田】売上'!E17+'【巣鴨】売上'!E17 -> 88822 | F17: ='【大井町】売上'!F17+'【蒲田】売上'!F17+'【巣鴨】売上'!F17 -> 63178 | G17: =SUM(D17+G16) -> 2691000 | H17: ='【大井町】売上'!H17+'【蒲田】売上'!H17+'【巣鴨】売上'!H17 -> 220000 | I17: =H17+I16 -> 3000000 | J17: =G17/I17 -> 0.897 | K17: =G17-I17 -> -309000 | L17: =M17/13 -> 90989.231 | M17: =F17+M16 -> 1182860
B18: ='【大井町】売上'!B18 -> 46068 | C18: ='【大井町】売上'!C18 -> 日 | D18: ='【大井町】売上'!D18+'【蒲田】売上'!D18+'【巣鴨】売上'!D18 -> 227000 | E18: ='【大井町】売上'!E18+'【蒲田】売上'!E18+'【巣鴨】売上'!E18 -> 123770 | F18: ='【大井町】売上'!F18+'【蒲田】売上'!F18+'【巣鴨】売上'!F18 -> 103230 | G18: =SUM(D18+G17) -> 2918000 | H18: ='【大井町】売上'!H18+'【蒲田】売上'!H18+'【巣鴨】売上'!H18 -> 220000 | I18: =H18+I17 -> 3220000 | J18: =G18/I18 -> 0.90621118 | K18: =G18-I18 -> -302000 | L18: =M18/14 -> 91863.571 | M18: =F18+M17 -> 1286090
B19: ='【大井町】売上'!B19 -> 46069 | C19: ='【大井町】売上'!C19 -> 月 | D19: ='【大井町】売上'!D19+'【蒲田】売上'!D19+'【巣鴨】売上'!D19 -> 212000 | E19: ='【大井町】売上'!E19+'【蒲田】売上'!E19+'【巣鴨】売上'!E19 -> 121000 | F19: ='【大井町】売上'!F19+'【蒲田】売上'!F19+'【巣鴨】売上'!F19 -> 91000 | G19: =SUM(D19+G18) -> 3130000 | H19: ='【大井町】売上'!H19+'【蒲田】売上'!H19+'【巣鴨】売上'!H19 -> 220000 | I19: =H19+I18 -> 3440000 | J19: =G19/I19 -> 0.90988372 | K19: =G19-I19 -> -310000 | L19: =M19/15 -> 91806 | M19: =F19+M18 -> 1377090
B20: ='【大井町】売上'!B20 -> 46070 | C20: ='【大井町】売上'!C20 -> 火 | D20: ='【大井町】売上'!D20+'【蒲田】売上'!D20+'【巣鴨】売上'!D20 -> 182000 | E20: ='【大井町】売上'!E20+'【蒲田】売上'!E20+'【巣鴨】売上'!E20 -> 106596 | F20: ='【大井町】売上'!F20+'【蒲田】売上'!F20+'【巣鴨】売上'!F20 -> 75404 | G20: =SUM(D20+G19) -> 3312000 | H20: ='【大井町】売上'!H20+'【蒲田】売上'!H20+'【巣鴨】売上'!H20 -> 220000 | I20: =H20+I19 -> 3660000 | J20: =G20/I20 -> 0.90491803 | K20: =G20-I20 -> -348000 | L20: =M20/16 -> 90780.875 | M20: =F20+M19 -> 1452494
B21: ='【大井町】売上'!B21 -> 46071 | C21: ='【大井町】売上'!C21 -> 水 | D21: ='【大井町】売上'!D21+'【蒲田】売上'!D21+'【巣鴨】売上'!D21 -> 179000 | E21: ='【大井町】売上'!E21+'【蒲田】売上'!E21+'【巣鴨】売上'!E21 -> 101500 | F21: ='【大井町】売上'!F21+'【蒲田】売上'!F21+'【巣鴨】売上'!F21 -> 77500 | G21: =SUM(D21+G20) -> 3491000 | H21: ='【大井町】売上'!H21+'【蒲田】売上'!H21+'【巣鴨】売上'!H21 -> 220000 | I21: =H21+I20 -> 3880000 | J21: =G21/I21 -> 0.89974227 | K21: =G21-I21 -> -389000 | L21: =M21/17 -> 89999.647 | M21: =F21+M20 -> 1529994
B22: ='【大井町】売上'!B22 -> 46072 | C22: ='【大井町】売上'!C22 -> 木 | D22: ='【大井町】売上'!D22+'【蒲田】売上'!D22+'【巣鴨】売上'!D22 -> 170000 | E22: ='【大井町】売上'!E22+'【蒲田】売上'!E22+'【巣鴨】売上'!E22 -> 99264 | F22: ='【大井町】売上'!F22+'【蒲田】売上'!F22+'【巣鴨】売上'!F22 -> 70736 | G22: =SUM(D22+G21) -> 3661000 | H22: ='【大井町】売上'!H22+'【蒲田】売上'!H22+'【巣鴨】売上'!H22 -> 220000 | I22: =H22+I21 -> 4100000 | J22: =G22/I22 -> 0.89292683 | K22: =G22-I22 -> -439000 | L22: =M22/18 -> 88929.444 | M22: =F22+M21 -> 1600730
B23: ='【大井町】売上'!B23 -> 46073 | C23: ='【大井町】売上'!C23 -> 金 | D23: ='【大井町】売上'!D23+'【蒲田】売上'!D23+'【巣鴨】売上'!D23 -> 197000 | E23: ='【大井町】売上'!E23+'【蒲田】売上'!E23+'【巣鴨】売上'!E23 -> 112019 | F23: ='【大井町】売上'!F23+'【蒲田】売上'!F23+'【巣鴨】売上'!F23 -> 84981 | G23: =SUM(D23+G22) -> 3858000 | H23: ='【大井町】売上'!H23+'【蒲田】売上'!H23+'【巣鴨】売上'!H23 -> 220000 | I23: =H23+I22 -> 4320000 | J23: =G23/I23 -> 0.89305556 | K23: =G23-I23 -> -462000 | L23: =M23/19 -> 88721.632 | M23: =F23+M22 -> 1685711
B24: ='【大井町】売上'!B24 -> 46074 | C24: ='【大井町】売上'!C24 -> 土 | D24: ='【大井町】売上'!D24+'【蒲田】売上'!D24+'【巣鴨】売上'!D24 -> 142000 | E24: ='【大井町】売上'!E24+'【蒲田】売上'!E24+'【巣鴨】売上'!E24 -> 81827 | F24: ='【大井町】売上'!F24+'【蒲田】売上'!F24+'【巣鴨】売上'!F24 -> 60173 | G24: =SUM(D24+G23) -> 4000000 | H24: ='【大井町】売上'!H24+'【蒲田】売上'!H24+'【巣鴨】売上'!H24 -> 220000 | I24: =H24+I23 -> 4540000 | J24: =G24/I24 -> 0.88105727 | K24: =G24-I24 -> -540000 | L24: =M24/20 -> 87294.2 | M24: =F24+M23 -> 1745884
B25: ='【大井町】売上'!B25 -> 46075 | C25: ='【大井町】売上'!C25 -> 日 | D25: ='【大井町】売上'!D25+'【蒲田】売上'!D25+'【巣鴨】売上'!D25 -> 123000 | E25: ='【大井町】売上'!E25+'【蒲田】売上'!E25+'【巣鴨】売上'!E25 -> 65500 | F25: ='【大井町】売上'!F25+'【蒲田】売上'!F25+'【巣鴨】売上'!F25 -> 57500 | G25: =SUM(D25+G24) -> 4123000 | H25: ='【大井町】売上'!H25+'【蒲田】売上'!H25+'【巣鴨】売上'!H25 -> 220000 | I25: =H25+I24 -> 4760000 | J25: =G25/I25 -> 0.86617647 | K25: =G25-I25 -> -637000 | L25: =M25/21 -> 85875.429 | M25: =F25+M24 -> 1803384
B26: ='【大井町】売上'!B26 -> 46076 | C26: ='【大井町】売上'!C26 -> 月 | D26: ='【大井町】売上'!D26+'【蒲田】売上'!D26+'【巣鴨】売上'!D26 -> 0 | E26: ='【大井町】売上'!E26+'【蒲田】売上'!E26+'【巣鴨】売上'!E26 -> 0 | F26: ='【大井町】売上'!F26+'【蒲田】売上'!F26+'【巣鴨】売上'!F26 -> 0 | G26: =SUM(D26+G25) -> 4123000 | H26: ='【大井町】売上'!H26+'【蒲田】売上'!H26+'【巣鴨】売上'!H26 -> 220000 | I26: =H26+I25 -> 4980000 | J26: =G26/I26 -> 0.82791165 | K26: =G26-I26 -> -857000 | L26: =M26/22 -> 81972 | M26: =F26+M25 -> 1803384
B27: ='【大井町】売上'!B27 -> 46077 | C27: ='【大井町】売上'!C27 -> 火 | D27: ='【大井町】売上'!D27+'【蒲田】売上'!D27+'【巣鴨】売上'!D27 -> 0 | E27: ='【大井町】売上'!E27+'【蒲田】売上'!E27+'【巣鴨】売上'!E27 -> 0 | F27: ='【大井町】売上'!F27+'【蒲田】売上'!F27+'【巣鴨】売上'!F27 -> 0 | G27: =SUM(D27+G26) -> 4123000 | H27: ='【大井町】売上'!H27+'【蒲田】売上'!H27+'【巣鴨】売上'!H27 -> 220000 | I27: =H27+I26 -> 5200000 | J27: =G27/I27 -> 0.79288462 | K27: =G27-I27 -> -1077000 | L27: =M27/23 -> 78408 | M27: =F27+M26 -> 1803384
B28: ='【大井町】売上'!B28 -> 46078 | C28: ='【大井町】売上'!C28 -> 水 | D28: ='【大井町】売上'!D28+'【蒲田】売上'!D28+'【巣鴨】売上'!D28 -> 0 | E28: ='【大井町】売上'!E28+'【蒲田】売上'!E28+'【巣鴨】売上'!E28 -> 0 | F28: ='【大井町】売上'!F28+'【蒲田】売上'!F28+'【巣鴨】売上'!F28 -> 0 | G28: =SUM(D28+G27) -> 4123000 | H28: ='【大井町】売上'!H28+'【蒲田】売上'!H28+'【巣鴨】売上'!H28 -> 220000 | I28: =H28+I27 -> 5420000 | J28: =G28/I28 -> 0.76070111 | K28: =G28-I28 -> -1297000 | L28: =M28/24 -> 75141 | M28: =F28+M27 -> 1803384
B29: ='【大井町】売上'!B29 -> 46079 | C29: ='【大井町】売上'!C29 -> 木 | D29: ='【大井町】売上'!D29+'【蒲田】売上'!D29+'【巣鴨】売上'!D29 -> 0 | E29: ='【大井町】売上'!E29+'【蒲田】売上'!E29+'【巣鴨】売上'!E29 -> 0 | F29: ='【大井町】売上'!F29+'【蒲田】売上'!F29+'【巣鴨】売上'!F29 -> 0 | G29: =SUM(D29+G28) -> 4123000 | H29: ='【大井町】売上'!H29+'【蒲田】売上'!H29+'【巣鴨】売上'!H29 -> 220000 | I29: =H29+I28 -> 5640000 | J29: =G29/I29 -> 0.73102837 | K29: =G29-I29 -> -1517000 | L29: =M29/25 -> 72135.36 | M29: =F29+M28 -> 1803384
B30: ='【大井町】売上'!B30 -> 46080 | C30: ='【大井町】売上'!C30 -> 金 | D30: ='【大井町】売上'!D30+'【蒲田】売上'!D30+'【巣鴨】売上'!D30 -> 0 | E30: ='【大井町】売上'!E30+'【蒲田】売上'!E30+'【巣鴨】売上'!E30 -> 0 | F30: ='【大井町】売上'!F30+'【蒲田】売上'!F30+'【巣鴨】売上'!F30 -> 0 | G30: =SUM(D30+G29) -> 4123000 | H30: ='【大井町】売上'!H30+'【蒲田】売上'!H30+'【巣鴨】売上'!H30 -> 220000 | I30: =H30+I29 -> 5860000 | J30: =G30/I30 -> 0.70358362 | K30: =G30-I30 -> -1737000 | L30: =M30/26 -> 69360.923 | M30: =F30+M29 -> 1803384
B31: ='【大井町】売上'!B31 -> 46081 | C31: ='【大井町】売上'!C31 -> 土 | D31: ='【大井町】売上'!D31+'【蒲田】売上'!D31+'【巣鴨】売上'!D31 -> 0 | E31: ='【大井町】売上'!E31+'【蒲田】売上'!E31+'【巣鴨】売上'!E31 -> 0 | F31: ='【大井町】売上'!F31+'【蒲田】売上'!F31+'【巣鴨】売上'!F31 -> 0 | G31: =SUM(D31+G30) -> 4123000 | H31: ='【大井町】売上'!H31+'【蒲田】売上'!H31+'【巣鴨】売上'!H31 -> 220000 | I31: =H31+I30 -> 6080000 | J31: =G31/I31 -> 0.678125 | K31: =G31-I31 -> -1957000 | L31: =M31/27 -> 66792 | M31: =F31+M30 -> 1803384
B32: ='【大井町】売上'!B32 | C32: ='【大井町】売上'!C32 | D32: ='【大井町】売上'!D32+'【蒲田】売上'!D32+'【巣鴨】売上'!D32 -> 0 | E32: ='【大井町】売上'!E32+'【蒲田】売上'!E32+'【巣鴨】売上'!E32 -> 0 | F32: ='【大井町】売上'!F32+'【蒲田】売上'!F32+'【巣鴨】売上'!F32 -> 0 | G32: =SUM(D32+G31) -> 4123000 | H32: ='【大井町】売上'!H32+'【蒲田】売上'!H32+'【巣鴨】売上'!H32 -> 220000 | I32: =H32+I31 -> 6300000 | J32: =G32/I32 -> 0.65444444 | K32: =G32-I32 -> -2177000 | L32: =M32/28 -> 64406.571 | M32: =F32+M31 -> 1803384
B33: ='【大井町】売上'!B33 | C33: ='【大井町】売上'!C33 | D33: ='【大井町】売上'!D33+'【蒲田】売上'!D33+'【巣鴨】売上'!D33 -> 0 | E33: ='【大井町】売上'!E33+'【蒲田】売上'!E33+'【巣鴨】売上'!E33 -> 0 | F33: ='【大井町】売上'!F33+'【蒲田】売上'!F33+'【巣鴨】売上'!F33 -> 0 | G33: =SUM(D33+G32) -> 4123000 | H33: ='【大井町】売上'!H33+'【蒲田】売上'!H33+'【巣鴨】売上'!H33 -> 220000 | I33: =H33+I32 -> 6520000 | J33: =G33/I33 -> 0.63236196 | K33: =G33-I33 -> -2397000 | L33: =M33/29 -> 62185.655 | M33: =F33+M32 -> 1803384
B34: ='【大井町】売上'!B34 | C34: ='【大井町】売上'!C34 | D34: ='【大井町】売上'!D34+'【蒲田】売上'!D34+'【巣鴨】売上'!D34 -> 0 | E34: ='【大井町】売上'!E34+'【蒲田】売上'!E34+'【巣鴨】売上'!E34 -> 0 | F34: ='【大井町】売上'!F34+'【蒲田】売上'!F34+'【巣鴨】売上'!F34 -> 0 | G34: =G33+D34 -> 4123000 | H34: ='【大井町】売上'!H34+'【蒲田】売上'!H34+'【巣鴨】売上'!H34 -> 220000 | I34: =H34+I33 -> 6740000 | J34: =G34/I34 -> 0.61172107 | K34: =G34-I34 -> -2617000 | L34: =M34/30 -> 60112.8 | M34: =F34+M33 -> 1803384
B35: 月合計 | D35: =SUM(D4:D34) -> 4123000 | E35: =SUM(E4:E34) -> 2319616 | F35: =SUM(D35-E35) -> 1803384 | G35: =SUM(G34) -> 4123000 | H35: =SUM(H4:H34) -> 6740000 | I35: =H35 -> 6740000

Sheet 【大井町】売上
B1: 46054
B3: 日時 | C3: 曜日 | D3: 実績 | E3: 取り分 | F3: 粗利 | G3: 実績累計 | H3: 予算 | I3: 予算累計 | J3: 進捗 | K3: 差異 | L3: 客単価 | M3: 新規 | N3: 顧客 | O3: 指名
B4: 46054 | C4: 日 | D4: ='シフト'!J7 -> 0 | E4: ='シフト'!K7 -> 0 | F4: =D4-E4 -> 0 | G4: =SUM(D4) -> 0 | I4: =SUM(H4) -> 0 | J4: =G4/I4 -> #DIV/0! | K4: =G4-I4 -> 0 | L4: =D4/SUM(M4:O4) -> #DIV/0! | M4: ='シフト'!N6 -> 0 | N4: ='シフト'!O6 -> 0 | O4: ='シフト'!P6 -> 0
B5: 46055 | C5: 月 | D5: ='シフト'!J12 -> 74000 | E5: ='シフト'!K12 -> 41000 | F5: =D5-E5 -> 33000 | G5: =SUM(D5+G4) -> 74000 | H5: 80000 | I5: =SUM(H5+I4) -> 80000 | J5: =G5/I5 -> 0.925 | K5: =G5-I5 -> -6000 | L5: =D5/SUM(M5:O5) -> 18500 | M5: ='シフト'!N11 -> 0 | N5: ='シフト'!O11 -> 4 | O5: ='シフト'!P11 -> 0
B6: 46056 | C6: 火 | D6: ='シフト'!J17 -> 90000 | E6: ='シフト'!K17 -> 47500 | F6: =D6-E6 -> 42500 | G6: =SUM(D6+G5) -> 164000 | H6: 80000 | I6: =SUM(H6+I5) -> 160000 | J6: =G6/I6 -> 1.025 | K6: =G6-I6 -> 4000 | L6: =D6/SUM(M6:O6) -> 22500 | M6: ='シフト'!N16 -> 0 | N6: ='シフト'!O16 -> 4 | O6: ='シフト'!P16 -> 0
B7: 46057 | C7: 水 | D7: ='シフト'!J22 -> 118000 | E7: ='シフト'!K22 -> 66500 | F7: =D7-E7 -> 51500 | G7: =SUM(D7+G6) -> 282000 | H7: 80000 | I7: =SUM(H7+I6) -> 240000 | J7: =G7/I7 -> 1.175 | K7: =G7-I7 -> 42000 | L7: =D7/SUM(M7:O7) -> 16857.143 | M7: ='シフト'!N21 -> 2 | N7: ='シフト'!O21 -> 3 | O7: ='シフト'!P21 -> 2
B8: 46058 | C8: 木 | D8: ='シフト'!J27 -> 131000 | E8: ='シフト'!K27 -> 77000 | F8: =D8-E8 -> 54000 | G8: =SUM(D8+G7) -> 413000 | H8: 80000 | I8: =SUM(H8+I7) -> 320000 | J8: =G8/I8 -> 1.290625 | K8: =G8-I8 -> 93000 | L8: =D8/SUM(M8:O8) -> 18714.286 | M8: ='シフト'!N26 -> 1 | N8: ='シフト'!O26 -> 3 | O8: ='シフト'!P26 -> 3
B9: 46059 | C9: 金 | D9: ='シフト'!J32 -> 57000 | E9: ='シフト'!K32 -> 33000 | F9: =D9-E9 -> 24000 | G9: =SUM(D9+G8) -> 470000 | H9: 80000 | I9: =SUM(H9+I8) -> 400000 | J9: =G9/I9 -> 1.175 | K9: =G9-I9 -> 70000 | L9: =D9/SUM(M9:O9) -> 14250 | M9: ='シフト'!N31 -> 1 | N9: ='シフト'!O31 -> 2 | O9: ='シフト'!P31 -> 1
B10: 46060 | C10: 土 | D10: ='シフト'!J37 -> 166000 | E10: ='シフト'!K37 -> 85000 | F10: =D10-E10 -> 81000 | G10: =SUM(D10+G9) -> 636000 | H10: 80000 | I10: =SUM(H10+I9) -> 480000 | J10: =G10/I10 -> 1.325 | K10: =G10-I10 -> 156000 | L10: =D10/SUM(M10:O10) -> 16600 | M10: ='シフト'!N36 -> 3 | N10: ='シフト'!O36 -> 7 | O10: ='シフト'!P36 -> 0
A11: =SUM(D4:D10) -> 636000 | B11: 46061 | C11: 日 | D11: ='シフト'!J42 -> 148000 | E11: ='シフト'!K42 -> 83500 | F11: =D11-E11 -> 64500 | G11: =SUM(D11+G10) -> 784000 | H11: 80000 | I11: =SUM(H11+I10) -> 560000 | J11: =G11/I11 -> 1.4 | K11: =G11-I11 -> 224000 | L11: =D11/SUM(M11:O11) -> 16444.444 | M11: ='シフト'!N41 -> 0 | N11: ='シフト'!O41 -> 4 | O11: ='シフト'!P41 -> 5
B12: 46062 | C12: 月 | D12: ='シフト'!J47 -> 55000 | E12: ='シフト'!K47 -> 31500 | F12: =D12-E12 -> 23500 | G12: =SUM(D12+G11) -> 839000 | H12: 80000 | I12: =SUM(H12+I11) -> 640000 | J12: =G12/I12 -> 1.3109375 | K12: =G12-I12 -> 199000 | L12: =D12/SUM(M12:O12) -> 18333.333 | M12: ='シフト'!N46 -> 0 | N12: ='シフト'!O46 -> 2 | O12: ='シフト'!P46 -> 1
B13: 46063 | C13: 火 | D13: ='シフト'!J52 -> 101000 | E13: ='シフト'!K52 -> 56500 | F13: =D13-E13 -> 44500 | G13: =SUM(D13+G12) -> 940000 | H13: 80000 | I13: =SUM(H13+I12) -> 720000 | J13: =G13/I13 -> 1.3055556 | K13: =G13-I13 -> 220000 | L13: =D13/SUM(M13:O13) -> 16833.333 | M13: ='シフト'!N51 -> 0 | N13: ='シフト'!O51 -> 4 | O13: ='シフト'!P51 -> 2
B14: 46064 | C14: 水 | D14: ='シフト'!J57 -> 63000 | E14: ='シフト'!K57 -> 35500 | F14: =D14-E14 -> 27500 | G14: =SUM(D14+G13) -> 1003000 | H14: 80000 | I14: =SUM(H14+I13) -> 800000 | J14: =G14/I14 -> 1.25375 | K14: =G14-I14 -> 203000 | L14: =D14/SUM(M14:O14) -> 15750 | M14: ='シフト'!N56 -> 0 | N14: ='シフト'!O56 -> 4 | O14: ='シフト'!P56 -> 0
B15: 46065 | C15: 木 | D15: ='シフト'!J62 -> 103000 | E15: ='シフト'!K62 -> 58500 | F15: =D15-E15 -> 44500 | G15: =SUM(D15+G14) -> 1106000 | H15: 80000 | I15: =SUM(H15+I14) -> 880000 | J15: =G15/I15 -> 1.2568182 | K15: =G15-I15 -> 226000 | L15: =D15/SUM(M15:O15) -> 17166.667 | M15: ='シフト'!N61 -> 1 | N15: ='シフト'!O61 -> 4 | O15: ='シフト'!P61 -> 1
B16: 46066 | C16: 金 | D16: ='シフト'!J67 -> 52000 | E16: ='シフト'!K67 -> 27000 | F16: =D16-E16 -> 25000 | G16: =SUM(D16+G15) -> 1158000 | H16: 80000 | I16: =SUM(H16+I15) -> 960000 | J16: =G16/I16 -> 1.20625 | K16: =G16-I16 -> 198000 | L16: =D16/SUM(M16:O16) -> 13000 | M16: ='シフト'!N66 -> 1 | N16: ='シフト'!O66 -> 0 | O16: ='シフト'!P66 -> 3
B17: 46067 | C17: 土 | D17: ='シフト'!J72 -> 76000 | E17: ='シフト'!K72 -> 41000 | F17: =D17-E17 -> 35000 | G17: =SUM(D17+G16) -> 1234000 | H17: 80000 | I17: =SUM(H17+I16) -> 1040000 | J17: =G17/I17 -> 1.1865385 | K17: =G17-I17 -> 194000 | L17: =D17/SUM(M17:O17) -> 15200 | M17: ='シフト'!N71 -> 0 | N17: ='シフト'!O71 -> 5 | O17: ='シフト'!P71 -> 0
A18: =SUM(D11:D17) -> 598000 | B18: 46068 | C18: 日 | D18: ='シフト'!J77 -> 76000 | E18: ='シフト'!K77 -> 46270 | F18: =D18-E18 -> 29730 | G18: =SUM(D18+G17) -> 1310000 | H18: 80000 | I18: =SUM(H18+I17) -> 1120000 | J18: =G18/I18 -> 1.1696429 | K18: =G18-I18 -> 190000 | L18: =D18/SUM(M18:O18) -> 15200 | M18: ='シフト'!N76 -> 1 | N18: ='シフト'!O76 -> 3 | O18: ='シフト'!P76 -> 1
B19: 46069 | C19: 月 | D19: ='シフト'!J82 -> 47000 | E19: ='シフト'!K82 -> 26500 | F19: =D19-E19 -> 20500 | G19: =SUM(D19+G18) -> 1357000 | H19: 80000 | I19: =SUM(H19+I18) -> 1200000 | J19: =G19/I19 -> 1.1308333 | K19: =G19-I19 -> 157000 | L19: =D19/SUM(M19:O19) -> 15666.667 | M19: ='シフト'!N81 -> 0 | N19: ='シフト'!O81 -> 2 | O19: ='シフト'!P81 -> 1
B20: 46070 | C20: 火 | D20: ='シフト'!J87 -> 64000 | E20: ='シフト'!K87 -> 35996 | F20: =D20-E20 -> 28004 | G20: =SUM(D20+G19) -> 1421000 | H20: 80000 | I20: =SUM(H20+I19) -> 1280000 | J20: =G20/I20 -> 1.1101562 | K20: =G20-I20 -> 141000 | L20: =D20/SUM(M20:O20) -> 16000 | M20: ='シフト'!N86 -> 1 | N20: ='シフト'!O86 -> 3 | O20: ='シフト'!P86 -> 0
B21: 46071 | C21: 水 | D21: ='シフト'!J92 -> 57000 | E21: ='シフト'!K92 -> 30500 | F21: =D21-E21 -> 26500 | G21: =SUM(D21+G20) -> 1478000 | H21: 80000 | I21: =SUM(H21+I20) -> 1360000 | J21: =G21/I21 -> 1.0867647 | K21: =G21-I21 -> 118000 | L21: =D21/SUM(M21:O21) -> 14250 | M21: ='シフト'!N91 -> 0 | N21: ='シフト'!O91 -> 3 | O21: ='シフト'!P91 -> 1
B22: 46072 | C22: 木 | D22: ='シフト'!J97 -> 44000 | E22: ='シフト'!K97 -> 25000 | F22: =D22-E22 -> 19000 | G22: =SUM(D22+G21) -> 1522000 | H22: 80000 | I22: =SUM(H22+I21) -> 1440000 | J22: =G22/I22 -> 1.0569444 | K22: =G22-I22 -> 82000 | L22: =D22/SUM(M22:O22) -> 14666.667 | M22: ='シフト'!N96 -> 0 | N22: ='シフト'!O96 -> 2 | O22: ='シフト'!P96 -> 1
B23: 46073 | C23: 金 | D23: ='シフト'!J102 -> 92000 | E23: ='シフト'!K102 -> 51000 | F23: =D23-E23 -> 41000 | G23: =SUM(D23+G22) -> 1614000 | H23: 80000 | I23: =SUM(H23+I22) -> 1520000 | J23: =G23/I23 -> 1.0618421 | K23: =G23-I23 -> 94000 | L23: =D23/SUM(M23:O23) -> 15333.333 | M23: ='シフト'!N101 -> 1 | N23: ='シフト'!O101 -> 2 | O23: ='シフト'!P101 -> 3
B24: 46074 | C24: 土 | D24: ='シフト'!J107 -> 96000 | E24: ='シフト'!K107 -> 55827 | F24: =D24-E24 -> 40173 | G24: =SUM(D24+G23) -> 1710000 | H24: 80000 | I24: =SUM(H24+I23) -> 1600000 | J24: =G24/I24 -> 1.06875 | K24: =G24-I24 -> 110000 | L24: =D24/SUM(M24:O24) -> 16000 | M24: ='シフト'!N106 -> 0 | N24: ='シフト'!O106 -> 4 | O24: ='シフト'!P106 -> 2
A25: =SUM(D18:D24) -> 476000 | B25: 46075 | C25: 日 | D25: ='シフト'!J112 -> 57000 | E25: ='シフト'!K112 -> 30500 | F25: =D25-E25 -> 26500 | G25: =SUM(D25+G24) -> 1767000 | H25: 80000 | I25: =SUM(H25+I24) -> 1680000 | J25: =G25/I25 -> 1.0517857 | K25: =G25-I25 -> 87000 | L25: =D25/SUM(M25:O25) -> 3.9299504 | M25: ='シフト'!N111 -> 1 | N25: ='シフト'!O111 -> 3 | O25: ='シフト'!P111 -> 14500
B26: 46076 | C26: 月 | D26: ='シフト'!J117 -> 0 | E26: ='シフト'!K117 -> 0 | F26: =D26-E26 -> 0 | G26: =SUM(D26+G25) -> 1767000 | H26: 80000 | I26: =SUM(H26+I25) -> 1760000 | J26: =G26/I26 -> 1.0039773 | K26: =G26-I26 -> 7000 | L26: =D26/SUM(M26:O26) -> #DIV/0! | M26: ='シフト'!N116 -> 0 | N26: ='シフト'!O116 -> 0 | O26: ='シフト'!P116 -> 0
B27: 46077 | C27: 火 | D27: ='シフト'!J122 -> 0 | E27: ='シフト'!K122 -> 0 | F27: =D27-E27 -> 0 | G27: =SUM(D27+G26) -> 1767000 | H27: 80000 | I27: =SUM(H27+I26) -> 1840000 | J27: =G27/I27 -> 0.96032609 | K27: =G27-I27 -> -73000 | L27: =D27/SUM(M27:O27) -> #DIV/0! | M27: ='シフト'!N121 -> 0 | N27: ='シフト'!O121 -> 0 | O27: ='シフト'!P121 -> 0
B28: 46078 | C28: 水 | D28: ='シフト'!J127 -> 0 | E28: ='シフト'!K127 -> 0 | F28: =D28-E28 -> 0 | G28: =SUM(D28+G27) -> 1767000 | H28: 80000 | I28: =SUM(H28+I27) -> 1920000 | J28: =G28/I28 -> 0.9203125 | K28: =G28-I28 -> -153000 | L28: =D28/SUM(M28:O28) -> 0 | M28: ='シフト'!N126 -> 0 | N28: ='シフト'!O126 -> 0 | O28: ='シフト'!P126 -> 1
B29: 46079 | C29: 木 | D29: ='シフト'!J132 -> 0 | E29: ='シフト'!K132 -> 0 | F29: =D29-E29 -> 0 | G29: =SUM(D29+G28) -> 1767000 | H29: 80000 | I29: =SUM(H29+I28) -> 2000000 | J29: =G29/I29 -> 0.8835 | K29: =G29-I29 -> -233000 | L29: =D29/SUM(M29:O29) -> 0 | M29: ='シフト'!N131 -> 0 | N29: ='シフト'!O131 -> 0 | O29: ='シフト'!P131 -> 2
B30: 46080 | C30: 金 | D30: ='シフト'!J137 -> 0 | E30: ='シフト'!K137 -> 0 | F30: =D30-E30 -> 0 | G30: =SUM(D30+G29) -> 1767000 | H30: 80000 | I30: =SUM(H30+I29) -> 2080000 | J30: =G30/I30 -> 0.84951923 | K30: =G30-I30 -> -313000 | L30: =D30/SUM(M30:O30) -> 0 | M30: ='シフト'!N136 -> 0 | N30: ='シフト'!O136 -> 0 | O30: ='シフト'!P136 -> 1
B31: 46081 | C31: 土 | D31: ='シフト'!J142 -> 0 | E31: ='シフト'!K142 -> 0 | F31: =D31-E31 -> 0 | G31: =SUM(D31+G30) -> 1767000 | H31: 80000 | I31: =SUM(H31+I30) -> 2160000 | J31: =G31/I31 -> 0.81805556 | K31: =G31-I31 -> -393000 | L31: =D31/SUM(M31:O31) -> #DIV/0! | M31: ='シフト'!N141 -> 0 | N31: ='シフト'!O141 -> 0 | O31: ='シフト'!P141 -> 0
A32: =SUM(D25:D31) -> 57000 | D32: ='シフト'!J147 -> 0 | E32: ='シフト'!K147 -> 0 | F32: =D32-E32 -> 0 | G32: =SUM(D32+G31) -> 1767000 | H32: 80000 | I32: =SUM(H32+I31) -> 2240000 | J32: =G32/I32 -> 0.78883929 | K32: =G32-I32 -> -473000 | L32: =D32/SUM(M32:O32) -> #DIV/0! | M32: ='シフト'!N146 -> 0 | N32: ='シフト'!O146 -> 0 | O32: ='シフト'!P146 -> 0
D33: ='シフト'!J152 -> 0 | E33: ='シフト'!K152 -> 0 | F33: =D33-E33 -> 0 | G33: =SUM(D33+G32) -> 1767000 | H33: 80000 | I33: =SUM(H33+I32) -> 2320000 | J33: =G33/I33 -> 0.76163793 | K33: =G33-I33 -> -553000 | L33: =D33/SUM(M33:O33) -> #DIV/0! | M33: ='シフト'!N151 -> 0 | N33: ='シフト'!O151 -> 0 | O33: ='シフト'!P151 -> 0
D34: ='シフト'!J157 -> 0 | E34: ='シフト'!K157 -> 0 | F34: =D34-E34 -> 0 | G34: =G33+D34 -> 1767000 | H34: 80000 | I34: =H34+I33 -> 2400000 | J34: =G34/I34 -> 0.73625 | K34: =G34-I34 -> -633000 | L34: =D34/SUM(M34:O34) -> 0 | M34: ='シフト'!N156 -> 0 | N34: ='シフト'!O156 -> 0 | O34: ='シフト'!P156 -> 1
B35: 月合計 | D35: =SUM(D4:D34) -> 1767000 | E35: =SUM(E4:E34) -> 985093 | F35: =SUM(D35-E35) -> 781907 | G35: =SUM(G34) -> 1767000 | H35: =SUM(H4:H34) -> 2400000 | I35: =I34 -> 2400000 | L35: =AVERAGEIF(L4:L34,"<>#DIV/0!") -> 13090.792 | M35: =SUM(M4:M34) -> 13 | N35: =SUM(N4:N34) -> 68 | O35: =SUM(O4:O34) -> 14532
I36: =I35+'【蒲田】売上'!I35+'【巣鴨】売上'!I35 -> 6740000 | M36: =M35/(M35+N35+O35) -> 0.00088961883 | N36: =N35/(M35+N35+O35) -> 0.0046533908 | O36: =O35/(M35+N35+O35) -> 0.99445699

Sheet シフト
D1: エステムプラザ501 | I1: スカイコート806
E2: 売上 | F2: 取り分 | G2: 粗利 | J2: 売上 | K2: 取り分 | L2: 粗利
A3: 1 | B3: ='【大井町】売上'!C4 -> 日 | C3: 早番 | D3: ='管理シフト'!D6 -> えみり | G3: =E3-F3 -> 0 | I3: ='管理シフト'!G6 -> みこ | L3: =J3-K3 -> 0
D4: 新規/顧客/指名 | I4: 新規/顧客/指名
C5: 遅番 | D5: ='管理シフト'!D7 -> しおん | G5: =E5-F5 -> 0 | I5: ='管理シフト'!G7 -> あんず | L5: =J5-K5 -> 0 | N5: 新規 | O5: 顧客 | P5: 指名
D6: 新規/顧客/指名 | I6: 新規/顧客/指名 | N6: =E4+E6+J4+J6 -> 0 | O6: =F4+F6+K4+K6 -> 0 | P6: =G4+G6+L4+L6 -> 0
J7: =E3+E5+J3+J5 -> 0 | K7: =F3+F5+K3+K5 -> 0 | L7: =SUM(G3+G5+L3+L5+Q3+Q5) -> 0
A8: 2 | B8: ='【大井町】売上'!C5 -> 月 | C8: 早番 | D8: ='管理シフト'!D9 -> ゆかり | G8: =E8-F8 -> 0 | I8: ='管理シフト'!G9 -> かずは | J8: 56000 | K8: 31000 | L8: =J8-K8 -> 25000
D9: 新規/顧客/指名 | I9: 新規/顧客/指名 | J9: 0 | K9: 3 | L9: 0
C10: 遅番 | D10: ='管理シフト'!D10 -> えみり | E10: 18000 | F10: 10000 | G10: =E10-F10 -> 8000 | I10: ='管理シフト'!G10 -> すみれ | L10: =J10-K10 -> 0 | N10: 新規 | O10: 顧客 | P10: 指名
D11: 新規/顧客/指名 | E11: 0 | F11: 1 | G11: 0 | I11: 新規/顧客/指名 | N11: =E9+E11+J9+J11 -> 0 | O11: =F9+F11+K9+K11 -> 4 | P11: =G9+G11+L9+L11 -> 0
J12: =E8+E10+J8+J10 -> 74000 | K12: =F8+F10+K8+K10 -> 41000 | L12: =SUM(G8+G10+L8+L10+Q8+Q10) -> 33000
A13: 3 | B13: ='【大井町】売上'!C6 -> 火 | C13: 早番 | D13: ='管理シフト'!D12 | E13: 26000 | F13: 13000 | G13: =E13-F13 -> 13000 | I13: ='管理シフト'!G12 -> ひより | L13: =J13-K13 -> 0
D14: 新規/顧客/指名 | E14: 0 | F14: 2 | G14: 0 | I14: 新規/顧客/指名
C15: 遅番 | D15: ='管理シフト'!D13 -> しのぶ | G15: =E15-F15 -> 0 | I15: ='管理シフト'!G13 | J15: 64000 | K15: 34500 | L15: =J15-K15 -> 29500 | N15: 新規 | O15: 顧客 | P15: 指名
D16: 新規/顧客/指名 | I16: 新規/顧客/指名 | J16: 0 | K16: 2 | L16: 0 | M16: 1 | N16: =E14+E16+J14+J16 -> 0 | O16: =F14+F16+K14+K16 -> 4 | P16: =G14+G16+L14+L16 -> 0
J17: =E13+E15+J13+J15 -> 90000 | K17: =F13+F15+K13+K15 -> 47500 | L17: =SUM(G13+G15+L13+L15+Q13+Q15) -> 42500
A18: 4 | B18: ='【大井町】売上'!C7 -> 水 | C18: 早番 | D18: ='管理シフト'!D15 | E18: 55000 | F18: 31000 | G18: =E18-F18 -> 24000 | I18: ='管理シフト'!G15 -> てるみ | J18: 43000 | K18: 23500 | L18: =J18-K18 -> 19500
D19: 新規/顧客/指名 | E19: 0 | F19: 2 | G19: 1 | I19: 新規/顧客/指名 | J19: 2 | K19: 1 | L19: 0
C20: 遅番 | D20: ='管理シフト'!D16 -> かすみ | E20: 20000 | F20: 12000 | G20: =E20-F20 -> 8000 | I20: ='管理シフト'!G16 -> えりか | L20: =J20-K20 -> 0 | N20: 新規 | O20: 顧客 | P20: 指名
D21: 新規/顧客/指名 | E21: 0 | F21: 0 | G21: 1 | I21: 新規/顧客/指名 | N21: =E19+E21+J19+J21 -> 2 | O21: =F19+F21+K19+K21 -> 3 | P21: =G19+G21+L19+L21 -> 2
J22: =E18+E20+J18+J20 -> 118000 | K22: =F18+F20+K18+K20 -> 66500 | L22: =SUM(G18+G20+L18+L20+Q18+Q20) -> 51500
A23: 5 | B23: ='【大井町】売上'!C8 -> 木 | C23: 早番 | D23: ='管理シフト'!D18 -> ますみ | E23: 95000 | F23: 57000 | G23: =E23-F23 -> 38000 | I23: ='管理シフト'!G18 | L23: =J23-K23 -> 0
D24: 新規/顧客/指名 | E24: 0 | F24: 2 | G24: 3 | I24: 新規/顧客/指名
C25: 遅番 | D25: ='管理シフト'!D19 -> ののは | G25: =E25-F25 -> 0 | I25: ='管理シフト'!G19 -> しおん | J25: 36000 | K25: 20000 | L25: =J25-K25 -> 16000 | N25: 新規 | O25: 顧客 | P25: 指名
D26: 新規/顧客/指名 | I26: 新規/顧客/指名 | J26: 1 | K26: 1 | L26: 0 | N26: =E24+E26+J24+J26 -> 1 | O26: =F24+F26+K24+K26 -> 3 | P26: =G24+G26+L24+L26 -> 3
J27: =E23+E25+J23+J25 -> 131000 | K27: =F23+F25+K23+K25 -> 77000 | L27: =SUM(G23+G25+L23+L25+Q23+Q25) -> 54000
A28: 6 | B28: ='【大井町】売上'!C9 -> 金 | C28: 早番 | D28: ='管理シフト'!D21 | E28: 17000 | F28: 11000 | G28: =E28-F28 -> 6000 | I28: ='管理シフト'!G21 -> ちなつ | L28: =J28-K28 -> 0
D29: 新規/顧客/指名 | E29: 0 | F29: 0 | G29: 1 | I29: 新規/顧客/指名
C30: 遅番 | D30: ='管理シフト'!D22 -> しずか | E30: 14000 | F30: 8000 | G30: =E30-F30 -> 6000 | I30: ='管理シフト'!G22 -> すみれ | J30: 26000 | K30: 14000 | L30: =J30-K30 -> 12000 | N30: 新規 | O30: 顧客 | P30: 指名
D31: 新規/顧客/指名 | E31: 0 | F31: 1 | G31: 0 | I31: 新規/顧客/指名 | J31: 1 | K31: 1 | L31: 0 | N31: =E29+E31+J29+J31 -> 1 | O31: =F29+F31+K29+K31 -> 2 | P31: =G29+G31+L29+L31 -> 1
J32: =E28+E30+J28+J30 -> 57000 | K32: =F28+F30+K28+K30 -> 33000 | L32: =SUM(G28+G30+L28+L30+Q28+Q30) -> 24000
A33: 7 | B33: ='【大井町】売上'!C10 -> 土 | C33: 早番 | D33: ='管理シフト'!D24 -> ゆかり | E33: 61000 | F33: 33500 | G33: =E33-F33 -> 27500 | I33: ='管理シフト'!G24 -> くれは | J33: 60000 | K33: 27000 | L33: =J33-K33 -> 33000
D34: 新規/顧客/指名 | E34: 0 | F34: 3 | G34: 0 | I34: 新規/顧客/指名 | J34: 2 | K34: 2 | L34: 0
C35: 遅番 | D35: ='管理シフト'!D25 -> わか | E35: 20000 | F35: 11000 | G35: =E35-F35 -> 9000 | I35: ='管理シフト'!G25 | J35: 25000 | K35: 13500 | L35: =J35-K35 -> 11500 | N35: 新規 | O35: 顧客 | P35: 指名
D36: 新規/顧客/指名 | E36: 0 | F36: 1 | G36: 0 | I36: 新規/顧客/指名 | J36: 1 | K36: 1 | L36: 0 | N36: =E34+E36+J34+J36 -> 3 | O36: =F34+F36+K34+K36 -> 7 | P36: =G34+G36+L34+L36 -> 0
J37: =E33+E35+J33+J35 -> 166000 | K37: =F33+F35+K33+K35 -> 85000 | L37: =SUM(G33+G35+L33+L35+Q33+Q35) -> 81000
A38: 8 | B38: ='【大井町】売上'!C11 -> 日 | C38: 早番 | D38: ='管理シフト'!D27 | E38: 43000 | F38: 23000 | G38: =E38-F38 -> 20000 | I38: ='管理シフト'!G27 | J38: 36000 | K38: 21000 | L38: =J38-K38 -> 15000
D39: 新規/顧客/指名 | E39: 0 | F39: 0 | G39: 3 | I39: 新規/顧客/指名 | J39: 0 | K39: 1 | L39: 1
C40: 遅番 | D40: ='管理シフト'!D28 -> ののは | E40: 69000 | F40: 39500 | G40: =E40-F40 -> 29500 | I40: ='管理シフト'!G28 -> しおん | L40: =J40-K40 -> 0 | N40: 新規 | O40: 顧客 | P40: 指名
D41: 新規/顧客/指名 | E41: 0 | F41: 3 | G41: 1 | I41: 新規/顧客/指名 | N41: =E39+E41+J39+J41 -> 0 | O41: =F39+F41+K39+K41 -> 4 | P41: =G39+G41+L39+L41 -> 5
J42: =E38+E40+J38+J40 -> 148000 | K42: =F38+F40+K38+K40 -> 83500 | L42: =SUM(G38+G40+L38+L40+Q38+Q40) -> 64500
A43: 9 | B43: ='【大井町】売上'!C12 -> 月 | C43: 早番 | D43: ='管理シフト'!D30 -> ひより | E43: 20000 | F43: 12000 | G43: =E43-F43 -> 8000 | I43: ='管理シフト'!G30 -> かずは | J43: 0 | K43: 0 | L43: =J43-K43 -> 0
D44: 新規/顧客/指名 | E44: 0 | F44: 0 | G44: 1 | I44: 新規/顧客/指名
C45: 遅番 | D45: ='管理シフト'!D31 -> かすみ | E45: 0 | F45: 0 | G45: =E45-F45 -> 0 | I45: ='管理シフト'!G31 | J45: 35000 | K45: 19500 | L45: =J45-K45 -> 15500 | N45: 新規 | O45: 顧客 | P45: 指名
D46: 新規/顧客/指名 | I46: 新規/顧客/指名 | J46: 0 | K46: 2 | L46: 0 | N46: =E44+E46+J44+J46 -> 0 | O46: =F44+F46+K44+K46 -> 2 | P46: =G44+G46+L44+L46 -> 1
J47: =E43+E45+J43+J45 -> 55000 | K47: =F43+F45+K43+K45 -> 31500 | L47: =SUM(G43+G45+L43+L45+Q43+Q45) -> 23500
A48: 10 | B48: ='【大井町】売上'!C13 -> 火 | C48: 早番 | D48: ='管理シフト'!D33 -> てるみ | E48: 15000 | F48: 8500 | G48: =E48-F48 -> 6500 | I48: ='管理シフト'!G33 | L48: =J48-K48 -> 0
D49: 新規/顧客/指名 | E49: 0 | F49: 1 | G49: 0 | I49: 新規/顧客/指名
C50: 遅番 | D50: ='管理シフト'!D34 | E50: 17000 | F50: 9000 | G50: =E50-F50 -> 8000 | I50: ='管理シフト'!G34 -> しのぶ | J50: 69000 | K50: 39000 | L50: =J50-K50 -> 30000 | N50: 新規 | O50: 顧客 | P50: 指名
D51: 新規/顧客/指名 | E51: 0 | F51: 0 | G51: 1 | I51: 新規/顧客/指名 | J51: 0 | K51: 3 | L51: 1 | N51: =E49+E51+J49+J51 -> 0 | O51: =F49+F51+K49+K51 -> 4 | P51: =G49+G51+L49+L51 -> 2
J52: =E48+E50+J48+J50 -> 101000 | K52: =F48+F50+K48+K50 -> 56500 | L52: =SUM(G48+G50+L48+L50+Q48+Q50) -> 44500
A53: 11 | B53: ='【大井町】売上'!C14 -> 水 | C53: 早番 | D53: ='管理シフト'!D36 | G53: =E53-F53 -> 0 | I53: ='管理シフト'!G36 | J53: 15000 | K53: 8500 | L53: =J53-K53 -> 6500
D54: 新規/顧客/指名 | I54: 新規/顧客/指名 | J54: 0 | K54: 1 | L54: 0
C55: 遅番 | D55: ='管理シフト'!D37 | E55: 48000 | F55: 27000 | G55: =E55-F55 -> 21000 | I55: ='管理シフト'!G37 | L55: =J55-K55 -> 0 | N55: 新規 | O55: 顧客 | P55: 指名
D56: 新規/顧客/指名 | E56: 0 | F56: 3 | G56: 0 | I56: 新規/顧客/指名 | N56: =E54+E56+J54+J56 -> 0 | O56: =F54+F56+K54+K56 -> 4 | P56: =G54+G56+L54+L56 -> 0
J57: =E53+E55+J53+J55 -> 63000 | K57: =F53+F55+K53+K55 -> 35500 | L57: =SUM(G53+G55+L53+L55+Q53+Q55) -> 27500
A58: 12 | B58: ='【大井町】売上'!C15 -> 木 | C58: 早番 | D58: ='管理シフト'!D39 | E58: 47000 | F58: 25500 | G58: =E58-F58 -> 21500 | I58: ='管理シフト'!G39 | J58: 38000 | K58: 23000 | L58: =J58-K58 -> 15000
D59: 新規/顧客/指名 | E59: 1 | F59: 2 | G59: 0 | I59: 新規/顧客/指名 | J59: 0 | K59: 1 | L59: 1
C60: 遅番 | D60: ='管理シフト'!D40 | G60: =E60-F60 -> 0 | I60: ='管理シフト'!G40 | J60: 18000 | K60: 10000 | L60: =J60-K60 -> 8000 | N60: 新規 | O60: 顧客 | P60: 指名
D61: 新規/顧客/指名 | I61: 新規/顧客/指名 | J61: 0 | K61: 1 | L61: 0 | N61: =E59+E61+J59+J61 -> 1 | O61: =F59+F61+K59+K61 -> 4 | P61: =G59+G61+L59+L61 -> 1
G62: =E62-F62 -> 0 | J62: =E58+E60+J58+J60 -> 103000 | K62: =F58+F60+K58+K60 -> 58500 | L62: =SUM(G58+G60+L58+L60+Q58+Q60) -> 44500
A63: 13 | B63: ='【大井町】売上'!C16 -> 金 | C63: 早番 | D63: ='管理シフト'!D42 | E63: 15000 | F63: 8500 | G63: =E63-F63 -> 6500 | I63: ='管理シフト'!G42 | J63: 24000 | K63: 12000 | L63: =J63-K63 -> 12000
D64: 新規/顧客/指名 | E64: 0 | F64: 0 | G64: 1 | I64: 新規/顧客/指名 | J64: 0 | K64: 0 | L64: 2
C65: 遅番 | D65: ='管理シフト'!D43 | E65: 13000 | F65: 6500 | G65: =E65-F65 -> 6500 | I65: ='管理シフト'!G43 | L65: =J65-K65 -> 0 | N65: 新規 | O65: 顧客 | P65: 指名
D66: 新規/顧客/指名 | E66: 1 | F66: 0 | G66: 0 | I66: 新規/顧客/指名 | N66: =E64+E66+J64+J66 -> 1 | O66: =F64+F66+K64+K66 -> 0 | P66: =G64+G66+L64+L66 -> 3
J67: =E63+E65+J63+J65 -> 52000 | K67: =F63+F65+K63+K65 -> 27000 | L67: =SUM(G63+G65+L63+L65+Q63+Q65) -> 25000
A68: 14 | B68: ='【大井町】売上'!C17 -> 土 | C68: 早番 | D68: ='管理シフト'!D45 | E68: 44000 | F68: 23000 | G68: =E68-F68 -> 21000 | I68: ='管理シフト'!G45 | L68: =J68-K68 -> 0
D69: 新規/顧客/指名 | E69: 0 | F69: 3 | G69: 0 | I69: 新規/顧客/指名
C70: 遅番 | D70: ='管理シフト'!D46 | G70: =E70-F70 -> 0 | I70: ='管理シフト'!G46 | J70: 32000 | K70: 18000 | L70: =J70-K70 -> 14000 | N70: 新規 | O70: 顧客 | P70: 指名
D71: 新規/顧客/指名 | I71: 新規/顧客/指名 | J71: 0 | K71: 2 | L71: 0 | N71: =E69+E71+J69+J71 -> 0 | O71: =F69+F71+K69+K71 -> 5 | P71: =G69+G71+L69+L71 -> 0
J72: =E68+E70+J68+J70 -> 76000 | K72: =F68+F70+K68+K70 -> 41000 | L72: =SUM(G68+G70+L68+L70+Q68+Q70) -> 35000
A73: 15 | B73: ='【大井町】売上'!C18 -> 日 | C73: 早番 | D73: ='管理シフト'!D49 | E73: 0 | F73: 0 | G73: =E73-F73 -> 0 | I73: ='管理シフト'!G49 | L73: =J73-K73 -> 0
D74: 新規/顧客/指名 | I74: 新規/顧客/指名
C75: 遅番 | D75: ='管理シフト'!D50 | E75: 35000 | F75: 19500 | G75: =E75-F75 -> 15500 | I75: ='管理シフト'!G50 | J75: 41000 | K75: 26770 | L75: =J75-K75 -> 14230 | N75: 新規 | O75: 顧客 | P75: 指名
D76: 新規/顧客/指名 | E76: 0 | F76: 2 | G76: 0 | I76: 新規/顧客/指名 | J76: 1 | K76: 1 | L76: 1 | N76: =E74+E76+J74+J76 -> 1 | O76: =F74+F76+K74+K76 -> 3 | P76: =G74+G76+L74+L76 -> 1
J77: =E73+E75+J73+J75 -> 76000 | K77: =F73+F75+K73+K75 -> 46270 | L77: =SUM(G73+G75+L73+L75+Q73+Q75) -> 29730
A78: 16 | B78: ='【大井町】売上'!C19 -> 月 | C78: 早番 | D78: ='管理シフト'!D52 | E78: 15000 | F78: 9000 | G78: =E78-F78 -> 6000 | I78: ='管理シフト'!G52 | J78: 20000 | K78: 11500 | L78: =J78-K78 -> 8500
D79: 新規/顧客/指名 | E79: 0 | F79: 0 | G79: 1 | I79: 新規/顧客/指名 | J79: 0 | K79: 1 | L79: 0
C80: 遅番 | D80: ='管理シフト'!D53 | I80: ='管理シフト'!G53 | J80: 12000 | K80: 6000 | L80: =J80-K80 -> 6000 | N80: 新規 | O80: 顧客 | P80: 指名
D81: 新規/顧客/指名 | I81: 新規/顧客/指名 | J81: 0 | K81: 1 | L81: 0 | N81: =E79+E81+J79+J81 -> 0 | O81: =F79+F81+K79+K81 -> 2 | P81: =G79+G81+L79+L81 -> 1
J82: =E78+E80+J78+J80 -> 47000 | K82: =F78+F80+K78+K80 -> 26500 | L82: =SUM(G78+G80+L78+L80+Q78+Q80) -> 20500
A83: 17 | B83: ='【大井町】売上'!C20 -> 火 | C83: 早番 | D83: ='管理シフト'!D55 | E83: 47000 | F83: 26996 | G83: =E83-F83 -> 20004 | I83: ='管理シフト'!G55 | L83: =J83-K83 -> 0
D84: 新規/顧客/指名 | E84: 1 | F84: 2 | G84: 0 | I84: 新規/顧客/指名
C85: 遅番 | D85: ='管理シフト'!D56 | G85: =E85-F85 -> 0 | I85: ='管理シフト'!G56 | J85: 17000 | K85: 9000 | L85: =J85-K85 -> 8000 | N85: 新規 | O85: 顧客 | P85: 指名
D86: 新規/顧客/指名 | I86: 新規/顧客/指名 | J86: 0 | K86: 1 | L86: 0 | N86: =E84+E86+J84+J86 -> 1 | O86: =F84+F86+K84+K86 -> 3 | P86: =G84+G86+L84+L86 -> 0
J87: =E83+E85+J83+J85 -> 64000 | K87: =F83+F85+K83+K85 -> 35996 | L87: =SUM(G83+G85+L83+L85+Q83+Q85) -> 28004
A88: 18 | B88: ='【大井町】売上'!C21 -> 水 | C88: 早番 | D88: ='管理シフト'!D58 | E88: 0 | F88: 0 | G88: =E88-F88 -> 0 | I88: ='管理シフト'!G58 | J88: 24000 | K88: 12000 | L88: =J88-K88 -> 12000
D89: 新規/顧客/指名 | I89: 新規/顧客/指名 | J89: 0 | K89: 1 | L89: 1
C90: 遅番 | D90: ='管理シフト'!D59 | E90: 33000 | F90: 18500 | G90: =E90-F90 -> 14500 | I90: ='管理シフト'!G59 | L90: =J90-K90 -> 0 | M90: 8番 | N90: 新規 | O90: 顧客 | P90: 指名
D91: 新規/顧客/指名 | E91: 0 | F91: 2 | G91: 0 | I91: 新規/顧客/指名 | N91: =E89+E91+J89+J91 -> 0 | O91: =F89+F91+K89+K91 -> 3 | P91: =G89+G91+L89+L91 -> 1
J92: =E88+E90+J88+J90 -> 57000 | K92: =F88+F90+K88+K90 -> 30500 | L92: =SUM(G88+G90+L88+L90+Q88+Q90) -> 26500
A93: 19 | B93: ='【大井町】売上'!C22 -> 木 | C93: 早番 | D93: ='管理シフト'!D61 | I93: ='管理シフト'!G61 | J93: 15000 | K93: 8500 | L93: =J93-K93 -> 6500
D94: 新規/顧客/指名 | G94: =E94-F94 -> 0 | I94: 新規/顧客/指名 | J94: 0 | K94: 1 | L94: 0
C95: 遅番 | D95: ='管理シフト'!D62 | E95: 29000 | F95: 16500 | G95: =E95-F95 -> 12500 | I95: ='管理シフト'!G62 | J95: 0 | K95: 0 | L95: =J95-K95 -> 0 | N95: 新規 | O95: 顧客 | P95: 指名
D96: 新規/顧客/指名 | E96: 0 | F96: 1 | G96: 1 | I96: 新規/顧客/指名 | N96: =E94+E96+J94+J96 -> 0 | O96: =F94+F96+K94+K96 -> 2 | P96: =G94+G96+L94+L96 -> 1
J97: =E93+E95+J93+J95 -> 44000 | K97: =F93+F95+K93+K95 -> 25000 | L97: =SUM(G93+G95+L93+L95+Q93+Q95) -> 19000
A98: 20 | B98: ='【大井町】売上'!C23 -> 金 | C98: 早番 | D98: ='管理シフト'!D64 | G98: =E98-F98 -> 0 | I98: ='管理シフト'!G64 | J98: 16000 | K98: 10000 | L98: =J98-K98 -> 6000
D99: 新規/顧客/指名 | I99: 新規/顧客/指名 | J99: 0 | K99: 0 | L99: 1
C100: 遅番 | D100: ='管理シフト'!D65 | E100: 46000 | F100: 26000 | G100: =E100-F100 -> 20000 | I100: ='管理シフト'!G65 | J100: 30000 | K100: 15000 | L100: =J100-K100 -> 15000 | N100: 新規 | O100: 顧客 | P100: 指名
...

Sheet 【蒲田】売上
B2: ='【大井町】売上'!B1 -> 46054
B3: 日時 | C3: 曜日 | D3: 実績 | E3: 取り分 | F3: 粗利 | G3: 実績累計 | H3: 予算 | I3: 予算累計 | K3: 差異 | L3: 客単価 | M3: 新規 | N3: 顧客 | O3: 指名
B4: ='【大井町】売上'!B4 -> 46054 | C4: ='【大井町】売上'!C4 -> 日 | D4: ='シフト2'!J7 -> 0 | E4: ='シフト2'!K7 -> 0 | F4: =D4-E4 -> 0 | G4: =SUM(D4) -> 0 | H4: 80000 | I4: =H4 -> 80000 | J4: =G4/I4 -> 0 | K4: =G4-I4 -> -80000 | L4: =D4/SUM(M4:O4) -> #DIV/0! | M4: ='シフト2'!N6 -> 0 | N4: ='シフト2'!O6 -> 0 | O4: ='シフト2'!P6 -> 0
B5: ='【大井町】売上'!B5 -> 46055 | C5: ='【大井町】売上'!C5 -> 月 | D5: ='シフト2'!J12 -> 82000 | E5: ='シフト2'!K12 -> 44500 | F5: =D5-E5 -> 37500 | G5: =SUM(D5+G4) -> 82000 | H5: 80000 | I5: =H5+I4 -> 160000 | J5: =G5/I5 -> 0.5125 | K5: =G5-I5 -> -78000 | L5: =D5/SUM(M5:O5) -> 16400 | M5: ='シフト2'!N11 -> 1 | N5: ='シフト2'!O11 -> 2 | O5: ='シフト2'!P11 -> 2
B6: ='【大井町】売上'!B6 -> 46056 | C6: ='【大井町】売上'!C6 -> 火 | D6: ='シフト2'!J17 -> 60000 | E6: ='シフト2'!K17 -> 34000 | F6: =D6-E6 -> 26000 | G6: =SUM(D6+G5) -> 142000 | H6: 80000 | I6: =H6+I5 -> 240000 | J6: =G6/I6 -> 0.59166667 | K6: =G6-I6 -> -98000 | L6: =D6/SUM(M6:O6) -> 15000 | M6: ='シフト2'!N16 -> 0 | N6: ='シフト2'!O16 -> 4 | O6: ='シフト2'!P16 -> 0
B7: ='【大井町】売上'!B7 -> 46057 | C7: ='【大井町】売上'!C7 -> 水 | D7: ='シフト2'!J22 -> 62000 | E7: ='シフト2'!K22 -> 35000 | F7: =D7-E7 -> 27000 | G7: =SUM(D7+G6) -> 204000 | H7: 80000 | I7: =H7+I6 -> 320000 | J7: =G7/I7 -> 0.6375 | K7: =G7-I7 -> -116000 | L7: =D7/SUM(M7:O7) -> 15500 | M7: ='シフト2'!N21 -> 1 | N7: ='シフト2'!O21 -> 3 | O7: ='シフト2'!P21 -> 0
B8: ='【大井町】売上'!B8 -> 46058 | C8: ='【大井町】売上'!C8 -> 木 | D8: ='シフト2'!J27 -> 89000 | E8: ='シフト2'!K27 -> 50925 | F8: =D8-E8 -> 38075 | G8: =SUM(D8+G7) -> 293000 | H8: 80000 | I8: =H8+I7 -> 400000 | J8: =G8/I8 -> 0.7325 | K8: =G8-I8 -> -107000 | L8: =D8/SUM(M8:O8) -> 14833.333 | M8: ='シフト2'!N26 -> 0 | N8: ='シフト2'!O26 -> 5 | O8: ='シフト2'!P26 -> 1
B9: ='【大井町】売上'!B9 -> 46059 | C9: ='【大井町】売上'!C9 -> 金 | D9: ='シフト2'!J32 -> 86000 | E9: ='シフト2'!K32 -> 45099 | F9: =D9-E9 -> 40901 | G9: =SUM(D9+G8) -> 379000 | H9: 80000 | I9: =H9+I8 -> 480000 | J9: =G9/I9 -> 0.78958333 | K9: =G9-I9 -> -101000 | L9: =D9/SUM(M9:O9) -> 17200 | M9: ='シフト2'!N31 -> 0 | N9: ='シフト2'!O31 -> 4 | O9: ='シフト2'!P31 -> 1
B10: ='【大井町】売上'!B10 -> 46060 | C10: ='【大井町】売上'!C10 -> 土 | D10: ='シフト2'!J37 -> 59000 | E10: ='シフト2'!K37 -> 34447 | F10: =D10-E10 -> 24553 | G10: =SUM(D10+G9) -> 438000 | H10: 80000 | I10: =H10+I9 -> 560000 | J10: =G10/I10 -> 0.78214286 | K10: =G10-I10 -> -122000 | L10: =D10/SUM(M10:O10) -> 14750 | M10: ='シフト2'!N36 -> 3 | N10: ='シフト2'!O36 -> 1 | O10: ='シフト2'!P36 -> 0
A11: =SUM(D4:D10) -> 438000 | B11: ='【大井町】売上'!B11 -> 46061 | C11: ='【大井町】売上'!C11 -> 日 | D11: ='シフト2'!J42 -> 30000 | E11: ='シフト2'!K42 -> 17000 | F11: =D11-E11 -> 13000 | G11: =SUM(D11+G10) -> 468000 | H11: 80000 | I11: =H11+I10 -> 640000 | J11: =G11/I11 -> 0.73125 | K11: =G11-I11 -> -172000 | L11: =D11/SUM(M11:O11) -> 15000 | M11: ='シフト2'!N41 -> 1 | N11: ='シフト2'!O41 -> 1 | O11: ='シフト2'!P41 -> 0
B12: ='【大井町】売上'!B12 -> 46062 | C12: ='【大井町】売上'!C12 -> 月 | D12: ='シフト2'!J47 -> 138000 | E12: ='シフト2'!K47 -> 77000 | F12: =D12-E12 -> 61000 | G12: =SUM(D12+G11) -> 606000 | H12: 80000 | I12: =H12+I11 -> 720000 | J12: =G12/I12 -> 0.84166667 | K12: =G12-I12 -> -114000 | L12: =D12/SUM(M12:O12) -> 17250 | M12: ='シフト2'!N46 -> 1 | N12: ='シフト2'!O46 -> 6 | O12: ='シフト2'!P46 -> 1
B13: ='【大井町】売上'!B13 -> 46063 | C13: ='【大井町】売上'!C13 -> 火 | D13: ='シフト2'!J52 -> 112000 | E13: ='シフト2'!K52 -> 61000 | F13: =D13-E13 -> 51000 | G13: =SUM(D13+G12) -> 718000 | H13: 80000 | I13: =H13+I12 -> 800000 | J13: =G13/I13 -> 0.8975 | K13: =G13-I13 -> -82000 | L13: =D13/SUM(M13:O13) -> 18666.667 | M13: ='シフト2'!N51 -> 3 | N13: ='シフト2'!O51 -> 3 | O13: ='シフト2'!P51 -> 0
B14: ='【大井町】売上'!B14 -> 46064 | C14: ='【大井町】売上'!C14 -> 水 | D14: ='シフト2'!J57 -> 73000 | E14: ='シフト2'!K57 -> 38500 | F14: =D14-E14 -> 34500 | G14: =SUM(D14+G13) -> 791000 | H14: 80000 | I14: =H14+I13 -> 880000 | J14: =G14/I14 -> 0.89886364 | K14: =G14-I14 -> -89000 | L14: =D14/SUM(M14:O14) -> 18250 | M14: ='シフト2'!N56 -> 1 | N14: ='シフト2'!O56 -> 3 | O14: ='シフト2'!P56 -> 0
B15: ='【大井町】売上'!B15 -> 46065 | C15: ='【大井町】売上'!C15 -> 木 | D15: ='シフト2'!J62 -> 97000 | E15: ='シフト2'!K62 -> 56847 | F15: =D15-E15 -> 40153 | G15: =SUM(D15+G14) -> 888000 | H15: 80000 | I15: =H15+I14 -> 960000 | J15: =G15/I15 -> 0.925 | K15: =G15-I15 -> -72000 | L15: =D15/SUM(M15:O15) -> 16166.667 | M15: ='シフト2'!N61 -> 0 | N15: ='シフト2'!O61 -> 4 | O15: ='シフト2'!P61 -> 2
B16: ='【大井町】売上'!B16 -> 46066 | C16: ='【大井町】売上'!C16 -> 金 | D16: ='シフト2'!J67 -> 51000 | E16: ='シフト2'!K67 -> 29000 | F16: =D16-E16 -> 22000 | G16: =SUM(D16+G15) -> 939000 | H16: 80000 | I16: =H16+I15 -> 1040000 | J16: =G16/I16 -> 0.90288462 | K16: =G16-I16 -> -101000 | L16: =D16/SUM(M16:O16) -> 17000 | M16: ='シフト2'!N66 -> 0 | N16: ='シフト2'!O66 -> 1 | O16: ='シフト2'!P66 -> 2
B17: ='【大井町】売上'!B17 -> 46067 | C17: ='【大井町】売上'!C17 -> 土 | D17: ='シフト2'!J72 -> 64000 | E17: ='シフト2'!K72 -> 40822 | F17: =D17-E17 -> 23178 | G17: =SUM(D17+G16) -> 1003000 | H17: 80000 | I17: =H17+I16 -> 1120000 | J17: =G17/I17 -> 0.89553571 | K17: =G17-I17 -> -117000 | L17: =D17/SUM(M17:O17) -> 21333.333 | M17: ='シフト2'!N71 -> 0 | N17: ='シフト2'!O71 -> 3 | O17: ='シフト2'!P71 -> 0
A18: =SUM(D11:D17) -> 565000 | B18: ='【大井町】売上'!B18 -> 46068 | C18: ='【大井町】売上'!C18 -> 日 | D18: ='シフト2'!J77 -> 68000 | E18: ='シフト2'!K77 -> 35000 | F18: =D18-E18 -> 33000 | G18: =SUM(D18+G17) -> 1071000 | H18: 80000 | I18: =H18+I17 -> 1200000 | J18: =G18/I18 -> 0.8925 | K18: =G18-I18 -> -129000 | L18: =D18/SUM(M18:O18) -> 17000 | M18: ='シフト2'!N76 -> 0 | N18: ='シフト2'!O76 -> 3 | O18: ='シフト2'!P76 -> 1
B19: ='【大井町】売上'!B19 -> 46069 | C19: ='【大井町】売上'!C19 -> 月 | D19: ='シフト2'!J82 -> 92000 | E19: ='シフト2'!K82 -> 52500 | F19: =D19-E19 -> 39500 | G19: =SUM(D19+G18) -> 1163000 | H19: 80000 | I19: =H19+I18 -> 1280000 | J19: =G19/I19 -> 0.90859375 | K19: =G19-I19 -> -117000 | L19: =D19/SUM(M19:O19) -> 18400 | M19: ='シフト2'!N81 -> 0 | N19: ='シフト2'!O81 -> 3 | O19: ='シフト2'!P81 -> 2
B20: ='【大井町】売上'!B20 -> 46070 | C20: ='【大井町】売上'!C20 -> 火 | D20: ='シフト2'!J87 -> 90000 | E20: ='シフト2'!K87 -> 53600 | F20: =D20-E20 -> 36400 | G20: =SUM(D20+G19) -> 1253000 | H20: 80000 | I20: =H20+I19 -> 1360000 | J20: =G20/I20 -> 0.92132353 | K20: =G20-I20 -> -107000 | L20: =D20/SUM(M20:O20) -> 15000 | M20: ='シフト2'!N86 -> 1 | N20: ='シフト2'!O86 -> 5 | O20: ='シフト2'!P86 -> 0
B21: ='【大井町】売上'!B21 -> 46071 | C21: ='【大井町】売上'!C21 -> 水 | D21: ='シフト2'!J92 -> 63000 | E21: ='シフト2'!K92 -> 36500 | F21: =D21-E21 -> 26500 | G21: =SUM(D21+G20) -> 1316000 | H21: 80000 | I21: =H21+I20 -> 1440000 | J21: =G21/I21 -> 0.91388889 | K21: =G21-I21 -> -124000 | L21: =D21/SUM(M21:O21) -> 15750 | M21: ='シフト2'!N91 -> 0 | N21: ='シフト2'!O91 -> 3 | O21: ='シフト2'!P91 -> 1
B22: ='【大井町】売上'!B22 -> 46072 | C22: ='【大井町】売上'!C22 -> 木 | D22: ='シフト2'!J97 -> 79000 | E22: ='シフト2'!K97 -> 45764 | F22: =D22-E22 -> 33236 | G22: =SUM(D22+G21) -> 1395000 | H22: 80000 | I22: =H22+I21 -> 1520000 | J22: =G22/I22 -> 0.91776316 | K22: =G22-I22 -> -125000 | L22: =D22/SUM(M22:O22) -> 15800 | M22: ='シフト2'!N96 -> 1 | N22: ='シフト2'!O96 -> 4 | O22: ='シフト2'!P96 -> 0
B23: ='【大井町】売上'!B23 -> 46073 | C23: ='【大井町】売上'!C23 -> 金 | D23: ='シフト2'!J102 -> 60000 | E23: ='シフト2'!K102 -> 33349 | F23: =D23-E23 -> 26651 | G23: =SUM(D23+G22) -> 1455000 | H23: 80000 | I23: =H23+I22 -> 1600000 | J23: =G23/I23 -> 0.909375 | K23: =G23-I23 -> -145000 | L23: =D23/SUM(M23:O23) -> 15000 | M23: ='シフト2'!N101 -> 0 | N23: ='シフト2'!O101 -> 2 | O23: ='シフト2'!P101 -> 2
B24: ='【大井町】売上'!B24 -> 46074 | C24: ='【大井町】売上'!C24 -> 土 | D24: ='シフト2'!J107 -> 46000 | E24: ='シフト2'!K107 -> 26000 | F24: =D24-E24 -> 20000 | G24: =SUM(D24+G23) -> 1501000 | H24: 80000 | I24: =H24+I23 -> 1680000 | J24: =G24/I24 -> 0.89345238 | K24: =G24-I24 -> -179000 | L24: =D24/SUM(M24:O24) -> 15333.333 | M24: ='シフト2'!N106 -> 2 | N24: ='シフト2'!O106 -> 0 | O24: ='シフト2'!P106 -> 1
A25: =SUM(D18:D24) -> 498000 | B25: ='【大井町】売上'!B25 -> 46075 | C25: ='【大井町】売上'!C25 -> 日 | D25: ='シフト2'!J112 -> 66000 | E25: ='シフト2'!K112 -> 35000 | F25: =D25-E25 -> 31000 | G25: =SUM(D25+G24) -> 1567000 | H25: 80000 | I25: =H25+I24 -> 1760000 | J25: =G25/I25 -> 0.89034091 | K25: =G25-I25 -> -193000 | L25: =D25/SUM(M25:O25) -> 13200 | M25: ='シフト2'!N111 -> 3 | N25: ='シフト2'!O111 -> 2 | O25: ='シフト2'!P111 -> 0
B26: ='【大井町】売上'!B26 -> 46076 | C26: ='【大井町】売上'!C26 -> 月 | D26: ='シフト2'!J117 -> 0 | E26: ='シフト2'!K117 -> 0 | F26: =D26-E26 -> 0 | G26: =SUM(D26+G25) -> 1567000 | H26: 80000 | I26: =H26+I25 -> 1840000 | J26: =G26/I26 -> 0.85163043 | K26: =G26-I26 -> -273000 | L26: =D26/SUM(M26:O26) -> #DIV/0! | M26: ='シフト2'!N116 -> 0 | N26: ='シフト2'!O116 -> 0 | O26: ='シフト2'!P116 -> 0
B27: ='【大井町】売上'!B27 -> 46077 | C27: ='【大井町】売上'!C27 -> 火 | D27: ='シフト2'!J122 -> 0 | E27: ='シフト2'!K122 -> 0 | F27: =D27-E27 -> 0 | G27: =SUM(D27+G26) -> 1567000 | H27: 80000 | I27: =H27+I26 -> 1920000 | J27: =G27/I27 -> 0.81614583 | K27: =G27-I27 -> -353000 | L27: =D27/SUM(M27:O27) -> #DIV/0! | M27: ='シフト2'!N121 -> 0 | N27: ='シフト2'!O121 -> 0 | O27: ='シフト2'!P121 -> 0
B28: ='【大井町】売上'!B28 -> 46078 | C28: ='【大井町】売上'!C28 -> 水 | D28: ='シフト2'!J127 -> 0 | E28: ='シフト2'!K127 -> 0 | F28: =D28-E28 -> 0 | G28: =SUM(D28+G27) -> 1567000 | H28: 80000 | I28: =H28+I27 -> 2000000 | J28: =G28/I28 -> 0.7835 | K28: =G28-I28 -> -433000 | L28: =D28/SUM(M28:O28) -> #DIV/0! | M28: ='シフト2'!N126 -> 0 | N28: ='シフト2'!O126 -> 0 | O28: ='シフト2'!P126 -> 0
B29: ='【大井町】売上'!B29 -> 46079 | C29: ='【大井町】売上'!C29 -> 木 | D29: ='シフト2'!J132 -> 0 | E29: ='シフト2'!K132 -> 0 | F29: =D29-E29 -> 0 | G29: =SUM(D29+G28) -> 1567000 | H29: 80000 | I29: =H29+I28 -> 2080000 | J29: =G29/I29 -> 0.75336538 | K29: =G29-I29 -> -513000 | L29: =D29/SUM(M29:O29) -> #DIV/0! | M29: ='シフト2'!N131 -> 0 | N29: ='シフト2'!O131 -> 0 | O29: ='シフト2'!P131 -> 0
B30: ='【大井町】売上'!B30 -> 46080 | C30: ='【大井町】売上'!C30 -> 金 | D30: ='シフト2'!J137 -> 0 | E30: ='シフト2'!K137 -> 0 | F30: =D30-E30 -> 0 | G30: =SUM(D30+G29) -> 1567000 | H30: 80000 | I30: =H30+I29 -> 2160000 | J30: =G30/I30 -> 0.72546296 | K30: =G30-I30 -> -593000 | L30: =D30/SUM(M30:O30) -> #DIV/0! | M30: ='シフト2'!N136 -> 0 | N30: ='シフト2'!O136 -> 0 | O30: ='シフト2'!P136 -> 0
B31: ='【大井町】売上'!B31 -> 46081 | C31: ='【大井町】売上'!C31 -> 土 | D31: ='シフト2'!J142 -> 0 | E31: ='シフト2'!K142 -> 0 | F31: =D31-E31 -> 0 | G31: =SUM(D31+G30) -> 1567000 | H31: 80000 | I31: =H31+I30 -> 2240000 | J31: =G31/I31 -> 0.69955357 | K31: =G31-I31 -> -673000 | L31: =D31/SUM(M31:O31) -> #DIV/0! | M31: ='シフト2'!N141 -> 0 | N31: ='シフト2'!O141 -> 0 | O31: ='シフト2'!P141 -> 0
A32: =SUM(D25:D31) -> 66000 | B32: ='【大井町】売上'!B32 | C32: ='【大井町】売上'!C32 | D32: ='シフト2'!J147 -> 0 | E32: ='シフト2'!K147 -> 0 | F32: =D32-E32 -> 0 | G32: =SUM(D32+G31) -> 1567000 | H32: 80000 | I32: =H32+I31 -> 2320000 | J32: =G32/I32 -> 0.67543103 | K32: =G32-I32 -> -753000 | L32: =D32/SUM(M32:O32) -> #DIV/0! | M32: ='シフト2'!N146 -> 0 | N32: ='シフト2'!O146 -> 0 | O32: ='シフト2'!P146 -> 0
A33: =SUM(D27:D33) -> 0 | B33: ='【大井町】売上'!B33 | C33: ='【大井町】売上'!C33 | D33: ='シフト2'!J152 -> 0 | E33: ='シフト2'!K152 -> 0 | F33: =D33-E33 -> 0 | G33: =SUM(D33+G32) -> 1567000 | H33: 80000 | I33: =H33+I32 -> 2400000 | J33: =G33/I33 -> 0.65291667 | K33: =G33-I33 -> -833000 | L33: =D33/SUM(M33:O33) -> #DIV/0! | M33: ='シフト2'!N151 -> 0 | N33: ='シフト2'!O151 -> 0 | O33: ='シフト2'!P151 -> 0
B34: ='【大井町】売上'!B34 | C34: ='【大井町】売上'!C34 | D34: ='シフト2'!J157 -> 0 | E34: ='シフト2'!K157 -> 0 | F34: =D34-E34 -> 0 | G34: =G33+D34 -> 1567000 | H34: 80000 | I34: =H34+I33 -> 2480000 | J34: =G34/I34 -> 0.63185484 | K34: =G34-I34 -> -913000 | L34: =D34/SUM(M34:O34) -> #DIV/0! | M34: ='シフト2'!N156 -> 0 | N34: ='シフト2'!O156 -> 0 | O34: ='シフト2'!P156 -> 0
B35: 月合計 | D35: =SUM(D4:D34) -> 1567000 | E35: =SUM(E4:E34) -> 881853 | F35: =SUM(D35-E35) -> 685147 | G35: =SUM(G34) -> 1567000 | H35: =SUM(H4:H34) -> 2480000 | I35: =H35 -> 2480000 | K35: 0 | L35: =AVERAGEIF(L4:L34,"<>#DIV/0!") -> 16325.397 | M35: =SUM(M4:M33) -> 18 | N35: =SUM(N4:N34) -> 62 | O35: =SUM(O4:O34) -> 16
M36: =M35/(M35+N35+O35) -> 0.1875 | N36: =N35/(M35+N35+O35) -> 0.64583333 | O36: =O35/(M35+N35+O35) -> 0.16666667

Sheet シフト2
D1: エルデューチェ303 | H1: レジディア1001
E2: 売上 | F2: 取り分 | G2: 粗利 | J2: 売上 | K2: 取り分 | L2: 粗利
A3: 1 | B3: ='【大井町】売上'!C4 -> 日 | C3: 早番 | D3: ='管理シフト'!J6 -> やすの | G3: =E3-F3 -> 0 | I3: ='管理シフト'!M6 -> まな | L3: =J3-K3 -> 0
D4: 新規/顧客/指名 | I4: 新規/顧客/指名
C5: 遅番 | D5: ='管理シフト'!J7 -> ののは | G5: =E5-F5 -> 0 | I5: ='管理シフト'!M7 | L5: =J5-K5 -> 0 | N5: 新規 | O5: 顧客 | P5: 指名
D6: 新規/顧客/指名 | I6: 新規/顧客/指名 | N6: =E4+E6+J4+J6 -> 0 | O6: =F4+F6+K4+K6 -> 0 | P6: =G4+G6+L4+L6 -> 0
J7: =E3+E5+J3+J5 -> 0 | K7: =F3+F5+K3+K5 -> 0 | L7: =SUM(G3+G5+L3+L5+Q3+Q5) -> 0
A8: 2 | B8: ='【大井町】売上'!C5 -> 月 | C8: 早番 | D8: ='管理シフト'!J9 | E8: 43000 | F8: 25000 | G8: =E8-F8 -> 18000 | I8: ='管理シフト'!M9 -> ちひろ | J8: 39000 | K8: 19500 | L8: =J8-K8 -> 19500
D9: 新規/顧客/指名 | E9: 0 | F9: 1 | G9: 2 | I9: 新規/顧客/指名 | J9: 1 | K9: 1 | L9: 0
C10: 遅番 | D10: ='管理シフト'!J10 -> しおん | G10: =E10-F10 -> 0 | I10: ='管理シフト'!M10 -> えりか | L10: =J10-K10 -> 0 | O10: 顧客 | P10: 指名
D11: 新規/顧客/指名 | I11: 新規/顧客/指名 | N11: =E9+E11+J9+J11 -> 1 | O11: =F9+F11+K9+K11 -> 2 | P11: =G9+G11+L9+L11 -> 2
J12: =E8+E10+J8+J10 -> 82000 | K12: =F8+F10+K8+K10 -> 44500 | L12: =SUM(G8+G10+L8+L10+Q8+Q10) -> 37500
A13: 3 | B13: ='【大井町】売上'!C6 -> 火 | C13: 早番 | D13: ='管理シフト'!J12 -> ますみ | E13: 20000 | F13: 11000 | G13: =E13-F13 -> 9000 | I13: ='管理シフト'!M12 -> てるみ | J13: 0 | K13: 0 | L13: =J13-K13 -> 0 | S13: x
D14: 新規/顧客/指名 | E14: 0 | F14: 1 | G14: 0 | I14: 新規/顧客/指名
C15: 遅番 | D15: ='管理シフト'!J13 -> すみれ | E15: 40000 | F15: 23000 | G15: =E15-F15 -> 17000 | I15: ='管理シフト'!M13 | L15: =J15-K15 -> 0 | N15: 新規 | O15: 顧客 | P15: 指名
D16: 新規/顧客/指名 | E16: 0 | F16: 3 | G16: 0 | I16: 新規/顧客/指名 | N16: =E14+E16+J14+J16 -> 0 | O16: =F14+F16+K14+K16 -> 4 | P16: =G14+G16+L14+L16 -> 0
J17: =E13+E15+J13+J15 -> 60000 | K17: =F13+F15+K13+K15 -> 34000 | L17: =SUM(G13+G15+L13+L15+Q13+Q15) -> 26000
A18: 4 | B18: ='【大井町】売上'!C7 -> 水 | C18: 早番 | D18: ='管理シフト'!J15 -> ゆかり | E18: 36000 | F18: 22000 | G18: =E18-F18 -> 14000 | I18: ='管理シフト'!M15 -> くれは | L18: =J18-K18 -> 0
E19: 0 | F19: 2 | G19: 0 | I19: 新規/顧客/指名
C20: 遅番 | D20: ='管理シフト'!J16 -> えみり | G20: =E20-F20 -> 0 | I20: ='管理シフト'!M16 | J20: 26000 | K20: 13000 | L20: =J20-K20 -> 13000 | N20: 新規 | O20: 顧客 | P20: 指名
D21: 新規/顧客/指名 | I21: 新規/顧客/指名 | J21: 1 | K21: 1 | L21: 0 | N21: =E19+E21+J19+J21 -> 1 | O21: =F19+F21+K19+K21 -> 3 | P21: =G19+G21+L19+L21 -> 0
J22: =E18+E20+J18+J20 -> 62000 | K22: =F18+F20+K18+K20 -> 35000 | L22: =SUM(G18+G20+L18+L20+Q18+Q20) -> 27000
A23: 5 | B23: ='【大井町】売上'!C8 -> 木 | C23: 早番 | D23: ='管理シフト'!J18 -> てるみ | E23: 30000 | F23: 17000 | G23: =E23-F23 -> 13000 | I23: ='管理シフト'!M18 -> ちひろ | J23: 45000 | K23: 25925 | L23: =J23-K23 -> 19075
D24: 新規/顧客/指名 | E24: 0 | F24: 2 | G24: 0 | I24: 新規/顧客/指名 | J24: 0 | K24: 3 | L24: 0
C25: 遅番 | D25: ='管理シフト'!J19 | E25: 0 | F25: 0 | G25: =E25-F25 -> 0 | I25: ='管理シフト'!M19 -> かずは | J25: 14000 | K25: 8000 | L25: =J25-K25 -> 6000 | N25: 新規 | O25: 顧客 | P25: 指名
D26: 新規/顧客/指名 | I26: 新規/顧客/指名 | J26: 0 | K26: 0 | L26: 1 | N26: =E24+E26+J24+J26 -> 0 | O26: =F24+F26+K24+K26 -> 5 | P26: =G24+G26+L24+L26 -> 1
J27: =E23+E25+J23+J25 -> 89000 | K27: =F23+F25+K23+K25 -> 50925 | L27: =SUM(G23+G25+L23+L25+Q23+Q25) -> 38075
A28: 6 | B28: ='【大井町】売上'!C9 -> 金 | C28: 早番 | D28: ='管理シフト'!J21 -> まな | E28: 12000 | F28: 6000 | G28: =E28-F28 -> 6000 | I28: ='管理シフト'!M21 -> ちひろ | L28: =J28-K28 -> 0
D29: 新規/顧客/指名 | E29: 0 | F29: 0 | G29: 1 | I29: 新規/顧客/指名
C30: 遅番 | D30: ='管理シフト'!J22 -> えりか | E30: 40000 | F30: 25099 | G30: =E30-F30 -> 14901 | I30: ='管理シフト'!M22 -> しのぶ | J30: 34000 | K30: 14000 | L30: =J30-K30 -> 20000 | N30: 新規 | O30: 顧客 | P30: 指名
D31: 新規/顧客/指名 | E31: 0 | F31: 2 | G31: 0 | I31: 新規/顧客/指名 | J31: 0 | K31: 2 | L31: 0 | N31: =E29+E31+J29+J31 -> 0 | O31: =F29+F31+K29+K31 -> 4 | P31: =G29+G31+L29+L31 -> 1
J32: =E28+E30+J28+J30 -> 86000 | K32: =F28+F30+K28+K30 -> 45099 | L32: =SUM(G28+G30+L28+L30+Q28+Q30) -> 40901
A33: 7 | B33: ='【大井町】売上'!C10 -> 土 | C33: 早番 | D33: ='管理シフト'!J24 -> てるみ | E33: 30000 | F33: 17000 | G33: =E33-F33 -> 13000 | I33: ='管理シフト'!M24 -> くみ | J33: 15000 | K33: 9447 | L33: =J33-K33 -> 5553
D34: 新規/顧客/指名 | E34: 1 | F34: 1 | G34: 0 | I34: 新規/顧客/指名 | J34: 1 | K34: 0 | L34: 0
C35: 遅番 | D35: ='管理シフト'!J25 | G35: =E35-F35 -> 0 | I35: ='管理シフト'!M25 -> かすみ | J35: 14000 | K35: 8000 | L35: =J35-K35 -> 6000 | N35: 新規 | O35: 顧客 | P35: 指名
D36: 新規/顧客/指名 | I36: 新規/顧客/指名 | J36: 1 | K36: 0 | L36: 0 | N36: =E34+E36+J34+J36 -> 3 | O36: =F34+F36+K34+K36 -> 1 | P36: =G34+G36+L34+L36 -> 0
J37: =E33+E35+J33+J35 -> 59000 | K37: =F33+F35+K33+K35 -> 34447 | L37: =SUM(G33+G35+L33+L35+Q33+Q35) -> 24553
A38: 8 | B38: ='【大井町】売上'!C11 -> 日 | C38: 早番 | D38: ='管理シフト'!J27 | E38: 15000 | F38: 8500 | G38: =E38-F38 -> 6500 | I38: ='管理シフト'!M27 -> ひより | L38: =J38-K38 -> 0 | Z38: --
D39: 新規/顧客/指名 | E39: 0 | F39: 1 | G39: 0 | I39: 新規/顧客/指名
C40: 遅番 | D40: ='管理シフト'!J28 -> わか | G40: =E40-F40 -> 0 | I40: ='管理シフト'!M28 | J40: 15000 | K40: 8500 | L40: =J40-K40 -> 6500 | N40: 新規 | O40: 顧客 | P40: 指名
D41: 新規/顧客/指名 | I41: 新規/顧客/指名 | J41: 1 | K41: 0 | L41: 0 | N41: =E39+E41+J39+J41 -> 1 | O41: =F39+F41+K39+K41 -> 1 | P41: =G39+G41+L39+L41 -> 0
J42: =E38+E40+J38+J40 -> 30000 | K42: =F38+F40+K38+K40 -> 17000 | L42: =SUM(G38+G40+L38+L40+Q38+Q40) -> 13000
A43: 9 | B43: ='【大井町】売上'!C12 -> 月 | C43: 早番 | D43: ='管理シフト'!J30 -> ゆかり | E43: 20000 | F43: 11000 | G43: =E43-F43 -> 9000 | I43: ='管理シフト'!M30 -> ちひろ | J43: 67000 | K43: 36500 | L43: =J43-K43 -> 30500
D44: 新規/顧客/指名 | E44: 1 | F44: 0 | G44: 0 | I44: 新規/顧客/指名 | J44: 0 | K44: 4 | L44: 0
C45: 遅番 | D45: ='管理シフト'!J31 -> みこ | E45: 51000 | F45: 29500 | G45: =E45-F45 -> 21500 | I45: ='管理シフト'!M31 -> しおん | L45: =J45-K45 -> 0 | N45: 新規 | O45: 顧客 | P45: 指名
D46: 新規/顧客/指名 | E46: 0 | F46: 2 | G46: 1 | I46: 新規/顧客/指名 | N46: =E44+E46+J44+J46 -> 1 | O46: =F44+F46+K44+K46 -> 6 | P46: =G44+G46+L44+L46 -> 1
J47: =E43+E45+J43+J45 -> 138000 | K47: =F43+F45+K43+K45 -> 77000 | L47: =SUM(G43+G45+L43+L45+Q43+Q45) -> 61000
A48: 10 | B48: ='【大井町】売上'!C13 -> 火 | C48: 早番 | D48: ='管理シフト'!J33 -> えみり | E48: 36000 | F48: 20000 | G48: =E48-F48 -> 16000 | I48: ='管理シフト'!M33 -> ひより | J48: 64000 | K48: 35000 | L48: =J48-K48 -> 29000
D49: 新規/顧客/指名 | E49: 1 | F49: 1 | G49: 0 | I49: 新規/顧客/指名 | J49: 2 | K49: 1 | L49: 0
C50: 遅番 | D50: ='管理シフト'!J34 | E50: 0 | F50: 0 | G50: =E50-F50 -> 0 | I50: ='管理シフト'!M34 -> しずか | J50: 12000 | K50: 6000 | L50: =J50-K50 -> 6000 | N50: 新規 | O50: 顧客 | P50: 指名
D51: 新規/顧客/指名 | I51: 新規/顧客/指名 | J51: 0 | K51: 1 | L51: 0 | N51: =E49+E51+J49+J51 -> 3 | O51: =F49+F51+K49+K51 -> 3 | P51: =G49+G51+L49+L51 -> 0
J52: =E48+E50+J48+J50 -> 112000 | K52: =F48+F50+K48+K50 -> 61000 | L52: =SUM(G48+G50+L48+L50+Q48+Q50) -> 51000
A53: 11 | B53: ='【大井町】売上'!C14 -> 水 | C53: 早番 | D53: ='管理シフト'!J36 | E53: 0 | F53: 0 | G53: =E53-F53 -> 0 | I53: ='管理シフト'!M36 | J53: 38000 | K53: 20000 | L53: =J53-K53 -> 18000
D54: 新規/顧客/指名 | I54: 新規/顧客/指名 | J54: 1 | K54: 1 | L54: 0
C55: 遅番 | D55: ='管理シフト'!J37 | E55: 16000 | F55: 8000 | G55: =E55-F55 -> 8000 | I55: ='管理シフト'!M37 | J55: 19000 | K55: 10500 | L55: =J55-K55 -> 8500 | N55: 新規 | O55: 顧客 | P55: 指名
D56: 新規/顧客/指名 | E56: 0 | F56: 1 | G56: 0 | I56: 新規/顧客/指名 | J56: 0 | K56: 1 | L56: 0 | N56: =E54+E56+J54+J56 -> 1 | O56: =F54+F56+K54+K56 -> 3 | P56: =G54+G56+L54+L56 -> 0
J57: =E53+E55+J53+J55 -> 73000 | K57: =F53+F55+K53+K55 -> 38500 | L57: =SUM(G53+G55+L53+L55+Q53+Q55) -> 34500
A58: 12 | B58: ='【大井町】売上'!C15 -> 木 | C58: 早番 | D58: ='管理シフト'!J39 | G58: =E58-F58 -> 0 | I58: ='管理シフト'!M39 | J58: 49000 | K58: 27847 | L58: =J58-K58 -> 21153
D59: 新規/顧客/指名 | I59: 新規/顧客/指名 | J59: 0 | K59: 3 | L59: 0
C60: 遅番 | D60: ='管理シフト'!J40 | E60: 48000 | F60: 29000 | G60: =E60-F60 -> 19000 | I60: ='管理シフト'!M40 | L60: =J60-K60 -> 0 | N60: 新規 | O60: 顧客 | P60: 指名
D61: 新規/顧客/指名 | E61: 0 | F61: 1 | G61: 2 | I61: 新規/顧客/指名 | N61: =E59+E61+J59+J61 -> 0 | O61: =F59+F61+K59+K61 -> 4 | P61: =G59+G61+L59+L61 -> 2
J62: =E58+E60+J58+J60 -> 97000 | K62: =F58+F60+K58+K60 -> 56847 | L62: =SUM(G58+G60+L58+L60+Q58+Q60) -> 40153
A63: 13 | B63: ='【大井町】売上'!C16 -> 金 | C63: 早番 | D63: ='管理シフト'!J42 | E63: 0 | F63: 0 | G63: =E63-F63 -> 0 | I63: ='管理シフト'!M42 | L63: =J63-K63 -> 0
D64: 新規/顧客/指名 | I64: 新規/顧客/指名
C65: 遅番 | D65: ='管理シフト'!J43 | G65: =E65-F65 -> 0 | I65: ='管理シフト'!M43 | J65: 51000 | K65: 29000 | L65: =J65-K65 -> 22000 | N65: 新規 | O65: 顧客 | P65: 指名
D66: 新規/顧客/指名 | I66: 新規/顧客/指名 | J66: 0 | K66: 1 | L66: 2 | N66: =E64+E66+J64+J66 -> 0 | O66: =F64+F66+K64+K66 -> 1 | P66: =G64+G66+L64+L66 -> 2
J67: =E63+E65+J63+J65 -> 51000 | K67: =F63+F65+K63+K65 -> 29000 | L67: =SUM(G63+G65+L63+L65+Q63+Q65) -> 22000
A68: 14 | B68: ='【大井町】売上'!C17 -> 土 | C68: 早番 | D68: ='管理シフト'!J45 | E68: 15000 | F68: 8500 | G68: =E68-F68 -> 6500 | I68: ='管理シフト'!M45 | J68: 29000 | K68: 15827 | L68: =J68-K68 -> 13173
D69: 新規/顧客/指名 | E69: 0 | F69: 1 | G69: 0 | I69: 新規/顧客/指名 | J69: 0 | K69: 1 | L69: 0
C70: 遅番 | D70: ='管理シフト'!J46 | G70: =E70-F70 -> 0 | I70: ='管理シフト'!M46 | J70: 20000 | K70: 16495 | L70: =J70-K70 -> 3505 | N70: 新規 | O70: 顧客 | P70: 指名
D71: 新規/顧客/指名 | I71: 新規/顧客/指名 | J71: 0 | K71: 1 | L71: 0 | N71: =E69+E71+J69+J71 -> 0 | O71: =F69+F71+K69+K71 -> 3 | P71: =G69+G71+L69+L71 -> 0
J72: =E68+E70+J68+J70 -> 64000 | K72: =F68+F70+K68+K70 -> 40822 | L72: =SUM(G68+G70+L68+L70+Q68+Q70) -> 23178
A73: 15 | B73: ='【大井町】売上'!C18 -> 日 | C73: 早番 | D73: ='管理シフト'!J49 | E73: 32000 | F73: 16000 | G73: =E73-F73 -> 16000 | I73: ='管理シフト'!M49 | J73: 19000 | K73: 10500 | L73: =J73-K73 -> 8500
D74: 新規/顧客/指名 | E74: 0 | F74: 1 | G74: 1 | I74: 新規/顧客/指名 | J74: 0 | K74: 1 | L74: 0
C75: 遅番 | D75: ='管理シフト'!J50 | E75: 0 | F75: 0 | G75: =E75-F75 -> 0 | I75: ='管理シフト'!M50 | J75: 17000 | K75: 8500 | L75: =J75-K75 -> 8500 | N75: 新規 | O75: 顧客 | P75: 指名
D76: 新規/顧客/指名 | I76: 新規/顧客/指名 | J76: 0 | K76: 1 | L76: 0 | N76: =E74+E76+J74+J76 -> 0 | O76: =F74+F76+K74+K76 -> 3 | P76: =G74+G76+L74+L76 -> 1
J77: =E73+E75+J73+J75 -> 68000 | K77: =F73+F75+K73+K75 -> 35000 | L77: =SUM(G73+G75+L73+L75+Q73+Q75) -> 33000
A78: 16 | B78: ='【大井町】売上'!C19 -> 月 | C78: 早番 | D78: ='管理シフト'!J52 | G78: =E78-F78 -> 0 | I78: ='管理シフト'!M52 | J78: 26000 | K78: 14000 | L78: =J78-K78 -> 12000
D79: 新規/顧客/指名 | I79: 新規/顧客/指名 | J79: 0 | K79: 0 | L79: 1
C80: 遅番 | D80: ='管理シフト'!J53 | E80: 32000 | F80: 19500 | G80: =E80-F80 -> 12500 | I80: ='管理シフト'!M53 | J80: 34000 | K80: 19000 | L80: =J80-K80 -> 15000 | N80: 新規 | O80: 顧客 | P80: 指名
D81: 新規/顧客/指名 | E81: 0 | F81: 1 | G81: 1 | I81: 新規/顧客/指名 | J81: 0 | K81: 2 | L81: 0 | N81: =E79+E81+J79+J81 -> 0 | O81: =F79+F81+K79+K81 -> 3 | P81: =G79+G81+L79+L81 -> 2
J82: =E78+E80+J78+J80 -> 92000 | K82: =F78+F80+K78+K80 -> 52500 | L82: =SUM(G78+G80+L78+L80+Q78+Q80) -> 39500
A83: 17 | B83: ='【大井町】売上'!C20 -> 火 | C83: 早番 | D83: ='管理シフト'!J55 | E83: 57000 | F83: 31500 | G83: =E83-F83 -> 25500 | I83: ='管理シフト'!M55 | J83: 15000 | K83: 8500 | L83: =J83-K83 -> 6500
D84: 新規/顧客/指名 | E84: 1 | F84: 3 | G84: 0 | I84: 新規/顧客/指名 | J84: 0 | K84: 1 | L84: 0
C85: 遅番 | D85: ='管理シフト'!J56 | G85: =E85-F85 -> 0 | I85: ='管理シフト'!M56 | J85: 18000 | K85: 13600 | L85: =J85-K85 -> 4400 | N85: 新規 | O85: 顧客 | P85: 指名
D86: 新規/顧客/指名 | I86: 新規/顧客/指名 | J86: 0 | K86: 1 | L86: 0 | N86: =E84+E86+J84+J86 -> 1 | O86: =F84+F86+K84+K86 -> 5 | P86: =G84+G86+L84+L86 -> 0
J87: =E83+E85+J83+J85 -> 90000 | K87: =F83+F85+K83+K85 -> 53600 | L87: =SUM(G83+G85+L83+L85+Q83+Q85) -> 36400
A88: 18 | B88: ='【大井町】売上'!C21 -> 水 | C88: 早番 | D88: ='管理シフト'!J58 | G88: =E88-F88 -> 0 | I88: ='管理シフト'!M58 | J88: 29000 | K88: 16500 | L88: =J88-K88 -> 12500
D89: 新規/顧客/指名 | I89: 新規/顧客/指名 | J89: 0 | K89: 2 | L89: 0
C90: 遅番 | D90: ='管理シフト'!J59 | E90: 34000 | F90: 20000 | G90: =E90-F90 -> 14000 | I90: ='管理シフト'!M59 | J90: 0 | K90: 0 | L90: =J90-K90 -> 0 | N90: 新規 | O90: 顧客 | P90: 指名
D91: 新規/顧客/指名 | E91: 0 | F91: 1 | G91: 1 | I91: 新規/顧客/指名 | N91: =E89+E91+J89+J91 -> 0 | O91: =F89+F91+K89+K91 -> 3 | P91: =G89+G91+L89+L91 -> 1
J92: =E88+E90+J88+J90 -> 63000 | K92: =F88+F90+K88+K90 -> 36500 | L92: =SUM(G88+G90+L88+L90+Q88+Q90) -> 26500
A93: 19 | B93: ='【大井町】売上'!C22 -> 木 | C93: 早番 | D93: ='管理シフト'!J61 | E93: 30000 | F93: 17772 | G93: =E93-F93 -> 12228 | I93: ='管理シフト'!M61 | J93: 35000 | K93: 19500 | L93: =J93-K93 -> 15500
D94: 新規/顧客/指名 | E94: 0 | F94: 2 | G94: 0 | I94: 新規/顧客/指名 | J94: 1 | K94: 1 | L94: 0
C95: 遅番 | D95: ='管理シフト'!J62 | G95: =E95-F95 -> 0 | I95: ='管理シフト'!M62 | J95: 14000 | K95: 8492 | L95: =J95-K95 -> 5508 | N95: 新規 | O95: 顧客 | P95: 指名
D96: 新規/顧客/指名 | I96: 新規/顧客/指名 | J96: 0 | K96: 1 | L96: 0 | N96: =E94+E96+J94+J96 -> 1 | O96: =F94+F96+K94+K96 -> 4 | P96: =G94+G96+L94+L96 -> 0
J97: =E93+E95+J93+J95 -> 79000 | K97: =F93+F95+K93+K95 -> 45764 | L97: =SUM(G93+G95+L93+L95+Q93+Q95) -> 33236
A98: 20 | B98: ='【大井町】売上'!C23 -> 金 | C98: 早番 | D98: ='管理シフト'!J64 | E98: 12000 | F98: 6000 | G98: =E98-F98 -> 6000 | I98: ='管理シフト'!M64 | J98: 15000 | K98: 8500 | L98: =J98-K98 -> 6500
D99: 新規/顧客/指名 | E99: 0 | F99: 1 | G99: 0 | I99: 新規/顧客/指名 | J99: 0 | K99: 1 | L99: 0
C100: 遅番 | D100: ='管理シフト'!J65 | E100: 14000 | F100: 7849 | G100: =E100-F100 -> 6151 | I100: ='管理シフト'!M65 | J100: 19000 | K100: 11000 | L100: =J100-K100 -> 8000 | N100: 新規 | O100: 顧客 | P100: 指名
...

Sheet 【巣鴨】売上
B2: ='【大井町】売上'!B1 -> 46054
B3: 日時 | C3: 曜日 | D3: 実績 | E3: 取り分 | F3: 粗利 | G3: 実績累計 | H3: 予算 | I3: 予算累計 | K3: 差異 | L3: 客単価 | M3: 新規 | N3: 顧客 | O3: 指名
B4: ='【大井町】売上'!B4 -> 46054 | C4: ='【大井町】売上'!C4 -> 日 | D4: ='シフト3'!J7 -> 0 | E4: ='シフト3'!K7 -> 0 | F4: =D4-E4 -> 0 | G4: =SUM(D4) -> 0 | H4: 60000 | I4: =H4 -> 60000 | J4: =G4/I4 -> 0 | K4: =G4-I4 -> -60000 | L4: =D4/SUM(M4:O4) -> #DIV/0! | M4: ='シフト2'!N6 -> 0 | N4: ='シフト2'!O6 -> 0 | O4: ='シフト3'!P6 -> 0
B5: ='【大井町】売上'!B5 -> 46055 | C5: ='【大井町】売上'!C5 -> 月 | D5: ='シフト3'!J12 -> 0 | E5: ='シフト3'!K12 -> 0 | F5: =D5-E5 -> 0 | G5: =SUM(D5+G4) -> 0 | H5: 60000 | I5: =H5+I4 -> 120000 | J5: =G5/I5 -> 0 | K5: =G5-I5 -> -120000 | L5: =D5/SUM(M5:O5) -> 0 | M5: ='シフト2'!N11 -> 1 | N5: ='シフト2'!O11 -> 2 | O5: ='シフト3'!P11 -> 0
B6: ='【大井町】売上'!B6 -> 46056 | C6: ='【大井町】売上'!C6 -> 火 | D6: ='シフト3'!J17 -> 74000 | E6: ='シフト3'!K17 -> 42500 | F6: =D6-E6 -> 31500 | G6: =SUM(D6+G5) -> 74000 | H6: 60000 | I6: =H6+I5 -> 180000 | J6: =G6/I6 -> 0.41111111 | K6: =G6-I6 -> -106000 | L6: =D6/SUM(M6:O6) -> 14800 | M6: ='シフト2'!N16 -> 0 | N6: ='シフト2'!O16 -> 4 | O6: ='シフト3'!P16 -> 1
B7: ='【大井町】売上'!B7 -> 46057 | C7: ='【大井町】売上'!C7 -> 水 | D7: ='シフト3'!J22 -> 27000 | E7: ='シフト3'!K22 -> 16000 | F7: =D7-E7 -> 11000 | G7: =SUM(D7+G6) -> 101000 | H7: 60000 | I7: =H7+I6 -> 240000 | J7: =G7/I7 -> 0.42083333 | K7: =G7-I7 -> -139000 | L7: =D7/SUM(M7:O7) -> 6750 | M7: ='シフト2'!N21 -> 1 | N7: ='シフト2'!O21 -> 3 | O7: ='シフト3'!P21 -> 0
B8: ='【大井町】売上'!B8 -> 46058 | C8: ='【大井町】売上'!C8 -> 木 | D8: ='シフト3'!J27 -> 0 | E8: ='シフト3'!K27 -> 0 | F8: =D8-E8 -> 0 | G8: =SUM(D8+G7) -> 101000 | H8: 60000 | I8: =H8+I7 -> 300000 | J8: =G8/I8 -> 0.33666667 | K8: =G8-I8 -> -199000 | L8: =D8/SUM(M8:O8) -> 0 | M8: ='シフト2'!N26 -> 0 | N8: ='シフト2'!O26 -> 5 | O8: ='シフト3'!P26 -> 0
B9: ='【大井町】売上'!B9 -> 46059 | C9: ='【大井町】売上'!C9 -> 金 | D9: ='シフト3'!J32 -> 73000 | E9: ='シフト3'!K32 -> 41000 | F9: =D9-E9 -> 32000 | G9: =SUM(D9+G8) -> 174000 | H9: 60000 | I9: =H9+I8 -> 360000 | J9: =G9/I9 -> 0.48333333 | K9: =G9-I9 -> -186000 | L9: =D9/SUM(M9:O9) -> 18250 | M9: ='シフト2'!N31 -> 0 | N9: ='シフト2'!O31 -> 4 | O9: ='シフト3'!P31 -> 0
B10: ='【大井町】売上'!B10 -> 46060 | C10: ='【大井町】売上'!C10 -> 土 | D10: ='シフト3'!J37 -> 37000 | E10: ='シフト3'!K37 -> 20500 | F10: =D10-E10 -> 16500 | G10: =SUM(D10+G9) -> 211000 | H10: 60000 | I10: =H10+I9 -> 420000 | J10: =G10/I10 -> 0.50238095 | K10: =G10-I10 -> -209000 | L10: =D10/SUM(M10:O10) -> 9250 | M10: ='シフト2'!N36 -> 3 | N10: ='シフト2'!O36 -> 1 | O10: ='シフト3'!P36 -> 0
A11: =SUM(D4:D10) -> 211000 | B11: ='【大井町】売上'!B11 -> 46061 | C11: ='【大井町】売上'!C11 -> 日 | D11: ='シフト3'!J42 -> 49000 | E11: ='シフト3'!K42 -> 28000 | F11: =D11-E11 -> 21000 | G11: =SUM(D11+G10) -> 260000 | H11: 60000 | I11: =H11+I10 -> 480000 | J11: =G11/I11 -> 0.54166667 | K11: =G11-I11 -> -220000 | L11: =D11/SUM(M11:O11) -> 24500 | M11: ='シフト2'!N41 -> 1 | N11: ='シフト2'!O41 -> 1 | O11: ='シフト3'!P41 -> 0
B12: ='【大井町】売上'!B12 -> 46062 | C12: ='【大井町】売上'!C12 -> 月 | D12: ='シフト3'!J47 -> 32000 | E12: ='シフト3'!K47 -> 17500 | F12: =D12-E12 -> 14500 | G12: =SUM(D12+G11) -> 292000 | H12: 60000 | I12: =H12+I11 -> 540000 | J12: =G12/I12 -> 0.54074074 | K12: =G12-I12 -> -248000 | L12: =D12/SUM(M12:O12) -> 4000 | M12: ='シフト2'!N46 -> 1 | N12: ='シフト2'!O46 -> 6 | O12: ='シフト3'!P46 -> 1
B13: ='【大井町】売上'!B13 -> 46063 | C13: ='【大井町】売上'!C13 -> 火 | D13: ='シフト3'!J52 -> 60000 | E13: ='シフト3'!K52 -> 35000 | F13: =D13-E13 -> 25000 | G13: =SUM(D13+G12) -> 352000 | H13: 60000 | I13: =H13+I12 -> 600000 | J13: =G13/I13 -> 0.58666667 | K13: =G13-I13 -> -248000 | L13: =D13/SUM(M13:O13) -> 8571.4286 | M13: ='シフト2'!N51 -> 3 | N13: ='シフト2'!O51 -> 3 | O13: ='シフト3'!P51 -> 1
B14: ='【大井町】売上'!B14 -> 46064 | C14: ='【大井町】売上'!C14 -> 水 | D14: ='シフト3'!J57 -> 35000 | E14: ='シフト3'!K57 -> 21000 | F14: =D14-E14 -> 14000 | G14: =SUM(D14+G13) -> 387000 | H14: 60000 | I14: =H14+I13 -> 660000 | J14: =G14/I14 -> 0.58636364 | K14: =G14-I14 -> -273000 | L14: =D14/SUM(M14:O14) -> 8750 | M14: ='シフト2'!N56 -> 1 | N14: ='シフト2'!O56 -> 3 | O14: ='シフト3'!P56 -> 0
B15: ='【大井町】売上'!B15 -> 46065 | C15: ='【大井町】売上'!C15 -> 木 | D15: ='シフト3'!J62 -> 25000 | E15: ='シフト3'!K62 -> 15000 | F15: =D15-E15 -> 10000 | G15: =SUM(D15+G14) -> 412000 | H15: 60000 | I15: =H15+I14 -> 720000 | J15: =G15/I15 -> 0.57222222 | K15: =G15-I15 -> -308000 | L15: =D15/SUM(M15:O15) -> 6250 | M15: ='シフト2'!N61 -> 0 | N15: ='シフト2'!O61 -> 4 | O15: ='シフト3'!P61 -> 0
B16: ='【大井町】売上'!B16 -> 46066 | C16: ='【大井町】売上'!C16 -> 金 | D16: ='シフト3'!J67 -> 30000 | E16: ='シフト3'!K67 -> 17000 | F16: =D16-E16 -> 13000 | G16: =SUM(D16+G15) -> 442000 | H16: 60000 | I16: =H16+I15 -> 780000 | J16: =G16/I16 -> 0.56666667 | K16: =G16-I16 -> -338000 | L16: =D16/SUM(M16:O16) -> 30000 | M16: ='シフト2'!N66 -> 0 | N16: ='シフト2'!O66 -> 1 | O16: ='シフト3'!P66 -> 0
B17: ='【大井町】売上'!B17 -> 46067 | C17: ='【大井町】売上'!C17 -> 土 | D17: ='シフト3'!J72 -> 12000 | E17: ='シフト3'!K72 -> 7000 | F17: =D17-E17 -> 5000 | G17: =SUM(D17+G16) -> 454000 | H17: 60000 | I17: =H17+I16 -> 840000 | J17: =G17/I17 -> 0.54047619 | K17: =G17-I17 -> -386000 | L17: =D17/SUM(M17:O17) -> 4000 | M17: ='シフト2'!N71 -> 0 | N17: ='シフト2'!O71 -> 3 | O17: ='シフト3'!P71 -> 0
A18: =SUM(D11:D17) -> 243000 | B18: ='【大井町】売上'!B18 -> 46068 | C18: ='【大井町】売上'!C18 -> 日 | D18: ='シフト3'!J77 -> 83000 | E18: ='シフト3'!K77 -> 42500 | F18: =D18-E18 -> 40500 | G18: =SUM(D18+G17) -> 537000 | H18: 60000 | I18: =H18+I17 -> 900000 | J18: =G18/I18 -> 0.59666667 | K18: =G18-I18 -> -363000 | L18: =D18/SUM(M18:O18) -> 27666.667 | M18: ='シフト2'!N76 -> 0 | N18: ='シフト2'!O76 -> 3 | O18: ='シフト3'!P76 -> 0
B19: ='【大井町】売上'!B19 -> 46069 | C19: ='【大井町】売上'!C19 -> 月 | D19: ='シフト3'!J82 -> 73000 | E19: ='シフト3'!K82 -> 42000 | F19: =D19-E19 -> 31000 | G19: =SUM(D19+G18) -> 610000 | H19: 60000 | I19: =H19+I18 -> 960000 | J19: =G19/I19 -> 0.63541667 | K19: =G19-I19 -> -350000 | L19: =D19/SUM(M19:O19) -> 24333.333 | M19: ='シフト2'!N81 -> 0 | N19: ='シフト2'!O81 -> 3 | O19: ='シフト3'!P81 -> 0
B20: ='【大井町】売上'!B20 -> 46070 | C20: ='【大井町】売上'!C20 -> 火 | D20: ='シフト3'!J87 -> 28000 | E20: ='シフト3'!K87 -> 17000 | F20: =D20-E20 -> 11000 | G20: =SUM(D20+G19) -> 638000 | H20: 60000 | I20: =H20+I19 -> 1020000 | J20: =G20/I20 -> 0.6254902 | K20: =G20-I20 -> -382000 | L20: =D20/SUM(M20:O20) -> 4666.6667 | M20: ='シフト2'!N86 -> 1 | N20: ='シフト2'!O86 -> 5 | O20: ='シフト3'!P86 -> 0
B21: ='【大井町】売上'!B21 -> 46071 | C21: ='【大井町】売上'!C21 -> 水 | D21: ='シフト3'!J92 -> 59000 | E21: ='シフト3'!K92 -> 34500 | F21: =D21-E21 -> 24500 | G21: =SUM(D21+G20) -> 697000 | H21: 60000 | I21: =H21+I20 -> 1080000 | J21: =G21/I21 -> 0.64537037 | K21: =G21-I21 -> -383000 | L21: =D21/SUM(M21:O21) -> 14750 | M21: ='シフト2'!N91 -> 0 | N21: ='シフト2'!O91 -> 3 | O21: ='シフト3'!P91 -> 1
B22: ='【大井町】売上'!B22 -> 46072 | C22: ='【大井町】売上'!C22 -> 木 | D22: ='シフト3'!J97 -> 47000 | E22: ='シフト3'!K97 -> 28500 | F22: =D22-E22 -> 18500 | G22: =SUM(D22+G21) -> 744000 | H22: 60000 | I22: =H22+I21 -> 1140000 | J22: =G22/I22 -> 0.65263158 | K22: =G22-I22 -> -396000 | L22: =D22/SUM(M22:O22) -> 9400 | M22: ='シフト2'!N96 -> 1 | N22: ='シフト2'!O96 -> 4 | O22: ='シフト3'!P96 -> 0
B23: ='【大井町】売上'!B23 -> 46073 | C23: ='【大井町】売上'!C23 -> 金 | D23: ='シフト3'!J102 -> 45000 | E23: ='シフト3'!K102 -> 27670 | F23: =D23-E23 -> 17330 | G23: =SUM(D23+G22) -> 789000 | H23: 60000 | I23: =H23+I22 -> 1200000 | J23: =G23/I23 -> 0.6575 | K23: =G23-I23 -> -411000 | L23: =D23/SUM(M23:O23) -> 15000 | M23: ='シフト2'!N101 -> 0 | N23: ='シフト2'!O101 -> 2 | O23: ='シフト3'!P101 -> 1
B24: ='【大井町】売上'!B24 -> 46074 | C24: ='【大井町】売上'!C24 -> 土 | D24: ='シフト3'!J107 -> 0 | E24: ='シフト3'!K107 -> 0 | F24: =D24-E24 -> 0 | G24: =SUM(D24+G23) -> 789000 | H24: 60000 | I24: =H24+I23 -> 1260000 | J24: =G24/I24 -> 0.62619048 | K24: =G24-I24 -> -471000 | L24: =D24/SUM(M24:O24) -> 0 | M24: ='シフト2'!N106 -> 2 | N24: ='シフト2'!O106 -> 0 | O24: ='シフト3'!P106 -> 0
A25: =SUM(D18:D24) -> 335000 | B25: ='【大井町】売上'!B25 -> 46075 | C25: ='【大井町】売上'!C25 -> 日 | D25: ='シフト3'!J112 -> 0 | E25: ='シフト3'!K112 -> 0 | F25: =D25-E25 -> 0 | G25: =SUM(D25+G24) -> 789000 | H25: 60000 | I25: =H25+I24 -> 1320000 | J25: =G25/I25 -> 0.59772727 | K25: =G25-I25 -> -531000 | L25: =D25/SUM(M25:O25) -> 0 | M25: ='シフト2'!N111 -> 3 | N25: ='シフト2'!O111 -> 2 | O25: ='シフト3'!P111 -> 0
B26: ='【大井町】売上'!B26 -> 46076 | C26: ='【大井町】売上'!C26 -> 月 | D26: ='シフト3'!J117 -> 0 | E26: ='シフト3'!K117 -> 0 | F26: =D26-E26 -> 0 | G26: =SUM(D26+G25) -> 789000 | H26: 60000 | I26: =H26+I25 -> 1380000 | J26: =G26/I26 -> 0.57173913 | K26: =G26-I26 -> -591000 | L26: =D26/SUM(M26:O26) -> #DIV/0! | M26: ='シフト2'!N116 -> 0 | N26: ='シフト2'!O116 -> 0 | O26: ='シフト3'!P116 -> 0
B27: ='【大井町】売上'!B27 -> 46077 | C27: ='【大井町】売上'!C27 -> 火 | D27: ='シフト3'!J122 -> 0 | E27: ='シフト3'!K122 -> 0 | F27: =D27-E27 -> 0 | G27: =SUM(D27+G26) -> 789000 | H27: 60000 | I27: =H27+I26 -> 1440000 | J27: =G27/I27 -> 0.54791667 | K27: =G27-I27 -> -651000 | L27: =D27/SUM(M27:O27) -> #DIV/0! | M27: ='シフト2'!N121 -> 0 | N27: ='シフト2'!O121 -> 0 | O27: ='シフト3'!P121 -> 0
B28: ='【大井町】売上'!B28 -> 46078 | C28: ='【大井町】売上'!C28 -> 水 | D28: ='シフト3'!J127 -> 0 | E28: ='シフト3'!K127 -> 0 | F28: =D28-E28 -> 0 | G28: =SUM(D28+G27) -> 789000 | H28: 60000 | I28: =H28+I27 -> 1500000 | J28: =G28/I28 -> 0.526 | K28: =G28-I28 -> -711000 | L28: =D28/SUM(M28:O28) -> #DIV/0! | M28: ='シフト2'!N126 -> 0 | N28: ='シフト2'!O126 -> 0 | O28: ='シフト3'!P126 -> 0
B29: ='【大井町】売上'!B29 -> 46079 | C29: ='【大井町】売上'!C29 -> 木 | D29: ='シフト3'!J132 -> 0 | E29: ='シフト3'!K132 -> 0 | F29: =D29-E29 -> 0 | G29: =SUM(D29+G28) -> 789000 | H29: 60000 | I29: =H29+I28 -> 1560000 | J29: =G29/I29 -> 0.50576923 | K29: =G29-I29 -> -771000 | L29: =D29/SUM(M29:O29) -> #DIV/0! | M29: ='シフト2'!N131 -> 0 | N29: ='シフト2'!O131 -> 0 | O29: ='シフト3'!P131 -> 0
B30: ='【大井町】売上'!B30 -> 46080 | C30: ='【大井町】売上'!C30 -> 金 | D30: ='シフト3'!J137 -> 0 | E30: ='シフト3'!K137 -> 0 | F30: =D30-E30 -> 0 | G30: =SUM(D30+G29) -> 789000 | H30: 60000 | I30: =H30+I29 -> 1620000 | J30: =G30/I30 -> 0.48703704 | K30: =G30-I30 -> -831000 | L30: =D30/SUM(M30:O30) -> #DIV/0! | M30: ='シフト2'!N136 -> 0 | N30: ='シフト2'!O136 -> 0 | O30: ='シフト3'!P136 -> 0
B31: ='【大井町】売上'!B31 -> 46081 | C31: ='【大井町】売上'!C31 -> 土 | D31: ='シフト3'!J142 -> 0 | E31: ='シフト3'!K142 -> 0 | F31: =D31-E31 -> 0 | G31: =SUM(D31+G30) -> 789000 | H31: 60000 | I31: =H31+I30 -> 1680000 | J31: =G31/I31 -> 0.46964286 | K31: =G31-I31 -> -891000 | L31: =D31/SUM(M31:O31) -> #DIV/0! | M31: ='シフト2'!N141 -> 0 | N31: ='シフト2'!O141 -> 0 | O31: ='シフト3'!P141 -> 0
A32: =SUM(D25:D31) -> 0 | B32: ='【大井町】売上'!B32 | C32: ='【大井町】売上'!C32 | D32: ='シフト3'!J147 -> 0 | E32: ='シフト3'!K147 -> 0 | F32: =D32-E32 -> 0 | G32: =SUM(D32+G31) -> 789000 | H32: 60000 | I32: =H32+I31 -> 1740000 | J32: =G32/I32 -> 0.45344828 | K32: =G32-I32 -> -951000 | L32: =D32/SUM(M32:O32) -> #DIV/0! | M32: ='シフト2'!N146 -> 0 | N32: ='シフト2'!O146 -> 0 | O32: ='シフト3'!P146 -> 0
A33: =SUM(D27:D33) -> 0 | B33: ='【大井町】売上'!B33 | C33: ='【大井町】売上'!C33 | D33: ='シフト3'!J152 -> 0 | E33: ='シフト3'!K152 -> 0 | F33: =D33-E33 -> 0 | G33: =SUM(D33+G32) -> 789000 | H33: 60000 | I33: =H33+I32 -> 1800000 | J33: =G33/I33 -> 0.43833333 | K33: =G33-I33 -> -1011000 | L33: =D33/SUM(M33:O33) -> #DIV/0! | M33: ='シフト2'!N151 -> 0 | N33: ='シフト2'!O151 -> 0 | O33: ='シフト3'!P151 -> 0
B34: ='【大井町】売上'!B34 | C34: ='【大井町】売上'!C34 | D34: ='シフト3'!J157 -> 0 | E34: ='シフト3'!K157 -> 0 | F34: =D34-E34 -> 0 | G34: =G33+D34 -> 789000 | H34: 60000 | I34: =H34+I33 -> 1860000 | J34: =G34/I34 -> 0.42419355 | K34: =G34-I34 -> -1071000 | L34: =D34/SUM(M34:O34) -> #DIV/0! | M34: ='シフト2'!N156 -> 0 | N34: ='シフト2'!O156 -> 0 | O34: ='シフト3'!P156 -> 0
B35: 月合計 | D35: =SUM(D4:D34) -> 789000 | E35: =SUM(E4:E34) -> 452670 | F35: =SUM(D35-E35) -> 336330 | G35: =SUM(G34) -> 789000 | H35: =SUM(H4:H34) -> 1860000 | I35: =H35 -> 1860000 | K35: 0 | L35: =AVERAGEIF(L4:L34,"<>#DIV/0!") -> 10997.052 | M35: =SUM(M4:M33) -> 18 | N35: =SUM(N4:N34) -> 62 | O35: =SUM(O4:O34) -> 5
M36: =M35/(M35+N35+O35) -> 0.21176471 | N36: =N35/(M35+N35+O35) -> 0.72941176 | O36: =O35/(M35+N35+O35) -> 0.058823529

Sheet シフト3
D1: XEBEC巣鴨203
E2: 売上 | F2: 取り分 | G2: 粗利 | J2: 売上 | K2: 取り分 | L2: 粗利
A3: 1 | B3: ='【大井町】売上'!C4 -> 日 | C3: 早番 | D3: ='管理シフト'!P6 | G3: =E3-F3 -> 0 | I3: ='管理シフト'!S6 -> てるみ | L3: =J3-K3 -> 0
D4: 新規/顧客/指名 | I4: 新規/顧客/指名
C5: 遅番 | D5: ='管理シフト'!P7 | G5: =E5-F5 -> 0 | I5: ='管理シフト'!S7 -> ののはダミー | L5: =J5-K5 -> 0 | N5: 新規 | O5: 顧客 | P5: 指名
D6: 新規/顧客/指名 | I6: 新規/顧客/指名 | N6: =E4+E6+J4+J6 -> 0 | O6: =F4+F6+K4+K6 -> 0 | P6: =G4+G6+L4+L6 -> 0
J7: =E3+E5+J3+J5 -> 0 | K7: =F3+F5+K3+K5 -> 0 | L7: =SUM(G3+G5+L3+L5+Q3+Q5) -> 0
A8: 2 | B8: ='【大井町】売上'!C5 -> 月 | C8: 早番 | D8: ='管理シフト'!P9 | G8: =E8-F8 -> 0 | I8: ='管理シフト'!S9 -> 南さなダミー | L8: =J8-K8 -> 0
D9: 新規/顧客/指名 | I9: 新規/顧客/指名
C10: 遅番 | D10: ='管理シフト'!P10 | G10: =E10-F10 -> 0 | I10: ='管理シフト'!S10 | L10: =J10-K10 -> 0 | O10: 顧客 | P10: 指名
D11: 新規/顧客/指名 | I11: 新規/顧客/指名 | N11: =E9+E11+J9+J11 -> 0 | O11: =F9+F11+K9+K11 -> 0 | P11: =G9+G11+L9+L11 -> 0
J12: =E8+E10+J8+J10 -> 0 | K12: =F8+F10+K8+K10 -> 0 | L12: =SUM(G8+G10+L8+L10+Q8+Q10) -> 0
A13: 3 | B13: ='【大井町】売上'!C6 -> 火 | C13: 早番 | D13: ='管理シフト'!P12 -> ゆかり | G13: =E13-F13 -> 0 | I13: ='管理シフト'!S12 | J13: 34000 | K13: 19000 | L13: =J13-K13 -> 15000 | S13: x
D14: 新規/顧客/指名 | I14: 新規/顧客/指名 | J14: 1 | K14: 1 | L14: 0
C15: 遅番 | D15: ='管理シフト'!P13 -> わかダミー | E15: 40000 | F15: 23500 | G15: =E15-F15 -> 16500 | I15: ='管理シフト'!S13 -> ほのか | L15: =J15-K15 -> 0 | N15: 新規 | O15: 顧客 | P15: 指名
D16: 新規/顧客/指名 | E16: 0 | F16: 1 | G16: 1 | I16: 新規/顧客/指名 | N16: =E14+E16+J14+J16 -> 1 | O16: =F14+F16+K14+K16 -> 2 | P16: =G14+G16+L14+L16 -> 1
J17: =E13+E15+J13+J15 -> 74000 | K17: =F13+F15+K13+K15 -> 42500 | L17: =SUM(G13+G15+L13+L15+Q13+Q15) -> 31500
A18: 4 | B18: ='【大井町】売上'!C7 -> 水 | C18: 早番 | D18: ='管理シフト'!P15 -> まな | G18: =E18-F18 -> 0 | I18: ='管理シフト'!S15 -> さな南ダミー | L18: =J18-K18 -> 0
D19: 新規/顧客/指名 | I19: 新規/顧客/指名
C20: 遅番 | D20: ='管理シフト'!P16 | E20: 27000 | F20: 16000 | G20: =E20-F20 -> 11000 | I20: ='管理シフト'!S16 | L20: =J20-K20 -> 0 | N20: 新規 | O20: 顧客 | P20: 指名
D21: 新規/顧客/指名 | E21: 2 | F21: 0 | G21: 0 | I21: 新規/顧客/指名 | N21: =E19+E21+J19+J21 -> 2 | O21: =F19+F21+K19+K21 -> 0 | P21: =G19+G21+L19+L21 -> 0
J22: =E18+E20+J18+J20 -> 27000 | K22: =F18+F20+K18+K20 -> 16000 | L22: =SUM(G18+G20+L18+L20+Q18+Q20) -> 11000
A23: 5 | B23: ='【大井町】売上'!C8 -> 木 | C23: 早番 | D23: ='管理シフト'!P18 -> あかりダミー | G23: =E23-F23 -> 0 | I23: ='管理シフト'!S18 | J23: 0 | K23: 0 | L23: =J23-K23 -> 0
D24: 新規/顧客/指名 | I24: 新規/顧客/指名
C25: 遅番 | D25: ='管理シフト'!P19 -> しずか | G25: =E25-F25 -> 0 | I25: ='管理シフト'!S19 | L25: =J25-K25 -> 0 | N25: 新規 | O25: 顧客 | P25: 指名
D26: 新規/顧客/指名 | I26: 新規/顧客/指名 | N26: =E24+E26+J24+J26 -> 0 | O26: =F24+F26+K24+K26 -> 0 | P26: =G24+G26+L24+L26 -> 0
J27: =E23+E25+J23+J25 -> 0 | K27: =F23+F25+K23+K25 -> 0 | L27: =SUM(G23+G25+L23+L25+Q23+Q25) -> 0
A28: 6 | B28: ='【大井町】売上'!C9 -> 金 | C28: 早番 | D28: ='管理シフト'!P21 | E28: 50000 | F28: 28000 | G28: =E28-F28 -> 22000 | I28: ='管理シフト'!S21 | J28: 10000 | K28: 6000 | L28: =J28-K28 -> 4000
D29: 新規/顧客/指名 | E29: 2 | F29: 1 | G29: 0 | I29: 新規/顧客/指名 | J29: 1 | K29: 0 | L29: 0
C30: 遅番 | D30: ='管理シフト'!P22 -> ほのか | E30: 0 | F30: 0 | G30: =E30-F30 -> 0 | I30: ='管理シフト'!S22 -> ちあき | J30: 13000 | K30: 7000 | L30: =J30-K30 -> 6000 | N30: 新規 | O30: 顧客 | P30: 指名
D31: 新規/顧客/指名 | J31: 1 | K31: 0 | L31: 0 | N31: =E29+E31+J29+J31 -> 4 | O31: =F29+F31+K29+K31 -> 1 | P31: =G29+G31+L29+L31 -> 0
J32: =E28+E30+J28+J30 -> 73000 | K32: =F28+F30+K28+K30 -> 41000 | L32: =SUM(G28+G30+L28+L30+Q28+Q30) -> 32000
A33: 7 | B33: ='【大井町】売上'!C10 -> 土 | C33: 早番 | D33: ='管理シフト'!P24 -> まな | E33: 37000 | F33: 20500 | G33: =E33-F33 -> 16500 | I33: ='管理シフト'!S24 -> かずは | L33: =J33-K33 -> 0
D34: 新規/顧客/指名 | E34: 1 | F34: 1 | G34: 0 | I34: 新規/顧客/指名
C35: 遅番 | D35: ='管理シフト'!P25 | G35: =E35-F35 -> 0 | I35: ='管理シフト'!S25 -> ゆい | L35: =J35-K35 -> 0 | N35: 新規 | O35: 顧客 | P35: 指名
D36: 新規/顧客/指名 | I36: 新規/顧客/指名 | N36: =E34+E36+J34+J36 -> 1 | O36: =F34+F36+K34+K36 -> 1 | P36: =G34+G36+L34+L36 -> 0
J37: =E33+E35+J33+J35 -> 37000 | K37: =F33+F35+K33+K35 -> 20500 | L37: =SUM(G33+G35+L33+L35+Q33+Q35) -> 16500
A38: 8 | B38: ='【大井町】売上'!C11 -> 日 | C38: 早番 | D38: ='管理シフト'!P27 | E38: 15000 | F38: 9000 | G38: =E38-F38 -> 6000 | I38: ='管理シフト'!S27 -> てるみ | J38: 34000 | K38: 19000 | L38: =J38-K38 -> 15000 | Z38: --
D39: 新規/顧客/指名 | E39: 0 | F39: 1 | G39: 0 | I39: 新規/顧客/指名 | J39: 0 | K39: 2 | L39: 0
C40: 遅番 | D40: ='管理シフト'!P28 | G40: =E40-F40 -> 0 | I40: ='管理シフト'!S28 | L40: =J40-K40 -> 0 | N40: 新規 | O40: 顧客 | P40: 指名
D41: 新規/顧客/指名 | I41: 新規/顧客/指名 | N41: =E39+E41+J39+J41 -> 0 | O41: =F39+F41+K39+K41 -> 3 | P41: =G39+G41+L39+L41 -> 0
J42: =E38+E40+J38+J40 -> 49000 | K42: =F38+F40+K38+K40 -> 28000 | L42: =SUM(G38+G40+L38+L40+Q38+Q40) -> 21000
A43: 9 | B43: ='【大井町】売上'!C12 -> 月 | C43: 早番 | D43: ='管理シフト'!P30 | E43: 0 | F43: 0 | G43: =E43-F43 -> 0 | I43: ='管理シフト'!S30 | L43: =J43-K43 -> 0
D44: 新規/顧客/指名 | I44: 新規/顧客/指名
C45: 遅番 | D45: ='管理シフト'!P31 | E45: 32000 | F45: 17500 | G45: =E45-F45 -> 14500 | I45: ='管理シフト'!S31 | J45: 0 | K45: 0 | L45: =J45-K45 -> 0 | N45: 新規 | O45: 顧客 | P45: 指名
D46: 新規/顧客/指名 | E46: 1 | F46: 0 | G46: 1 | I46: 新規/顧客/指名 | N46: =E44+E46+J44+J46 -> 1 | O46: =F44+F46+K44+K46 -> 0 | P46: =G44+G46+L44+L46 -> 1
J47: =E43+E45+J43+J45 -> 32000 | K47: =F43+F45+K43+K45 -> 17500 | L47: =SUM(G43+G45+L43+L45+Q43+Q45) -> 14500
A48: 10 | B48: ='【大井町】売上'!C13 -> 火 | C48: 早番 | D48: ='管理シフト'!P33 -> まな | E48: 44000 | F48: 25000 | G48: =E48-F48 -> 19000 | I48: ='管理シフト'!S33 | L48: =J48-K48 -> 0
D49: 新規/顧客/指名 | E49: 2 | F49: 1 | G49: 0 | I49: 新規/顧客/指名
C50: 遅番 | D50: ='管理シフト'!P34 | E50: 0 | F50: 0 | G50: =E50-F50 -> 0 | I50: ='管理シフト'!S34 -> かずは | J50: 16000 | K50: 10000 | L50: =J50-K50 -> 6000 | N50: 新規 | O50: 顧客 | P50: 指名
D51: 新規/顧客/指名 | I51: 新規/顧客/指名 | J51: 0 | K51: 0 | L51: 1 | N51: =E49+E51+J49+J51 -> 2 | O51: =F49+F51+K49+K51 -> 1 | P51: =G49+G51+L49+L51 -> 1
J52: =E48+E50+J48+J50 -> 60000 | K52: =F48+F50+K48+K50 -> 35000 | L52: =SUM(G48+G50+L48+L50+Q48+Q50) -> 25000
A53: 11 | B53: ='【大井町】売上'!C14 -> 水 | C53: 早番 | D53: ='管理シフト'!P36 | E53: 0 | F53: 0 | G53: =E53-F53 -> 0 | I53: ='管理シフト'!S36 | L53: =J53-K53 -> 0
D54: 新規/顧客/指名 | I54: 新規/顧客/指名
C55: 遅番 | D55: ='管理シフト'!P37 | G55: =E55-F55 -> 0 | I55: ='管理シフト'!S37 | J55: 35000 | K55: 21000 | L55: =J55-K55 -> 14000 | N55: 新規 | O55: 顧客 | P55: 指名
D56: 新規/顧客/指名 | I56: 新規/顧客/指名 | J56: 0 | K56: 2 | L56: 0 | N56: =E54+E56+J54+J56 -> 0 | O56: =F54+F56+K54+K56 -> 2 | P56: =G54+G56+L54+L56 -> 0
J57: =E53+E55+J53+J55 -> 35000 | K57: =F53+F55+K53+K55 -> 21000 | L57: =SUM(G53+G55+L53+L55+Q53+Q55) -> 14000
A58: 12 | B58: ='【大井町】売上'!C15 -> 木 | C58: 早番 | D58: ='管理シフト'!P39 | G58: =E58-F58 -> 0 | I58: ='管理シフト'!S39 | L58: =J58-K58 -> 0
D59: 新規/顧客/指名 | I59: 新規/顧客/指名
C60: 遅番 | D60: ='管理シフト'!P40 | E60: 25000 | F60: 15000 | G60: =E60-F60 -> 10000 | I60: ='管理シフト'!S40 | L60: =J60-K60 -> 0 | N60: 新規 | O60: 顧客 | P60: 指名
D61: 新規/顧客/指名 | E61: 1 | F61: 1 | G61: 0 | I61: 新規/顧客/指名 | N61: =E59+E61+J59+J61 -> 1 | O61: =F59+F61+K59+K61 -> 1 | P61: =G59+G61+L59+L61 -> 0
J62: =E58+E60+J58+J60 -> 25000 | K62: =F58+F60+K58+K60 -> 15000 | L62: =SUM(G58+G60+L58+L60+Q58+Q60) -> 10000
A63: 13 | B63: ='【大井町】売上'!C16 -> 金 | C63: 早番 | D63: ='管理シフト'!P42 | G63: =E63-F63 -> 0 | I63: ='管理シフト'!S42 | L63: =J63-K63 -> 0
D64: 新規/顧客/指名 | I64: 新規/顧客/指名
C65: 遅番 | D65: ='管理シフト'!P43 | G65: =E65-F65 -> 0 | I65: ='管理シフト'!S43 | J65: 30000 | K65: 17000 | L65: =J65-K65 -> 13000 | N65: 新規 | O65: 顧客 | P65: 指名
D66: 新規/顧客/指名 | I66: 新規/顧客/指名 | J66: 1 | K66: 1 | L66: 0 | N66: =E64+E66+J64+J66 -> 1 | O66: =F64+F66+K64+K66 -> 1 | P66: =G64+G66+L64+L66 -> 0
J67: =E63+E65+J63+J65 -> 30000 | K67: =F63+F65+K63+K65 -> 17000 | L67: =SUM(G63+G65+L63+L65+Q63+Q65) -> 13000
A68: 14 | B68: ='【大井町】売上'!C17 -> 土 | C68: 早番 | D68: ='管理シフト'!P45 | G68: =E68-F68 -> 0 | I68: ='管理シフト'!S45 | L68: =J68-K68 -> 0
D69: 新規/顧客/指名 | I69: 新規/顧客/指名
C70: 遅番 | D70: ='管理シフト'!P46 | E70: 12000 | F70: 7000 | G70: =E70-F70 -> 5000 | I70: ='管理シフト'!S46 | L70: =J70-K70 -> 0 | N70: 新規 | O70: 顧客 | P70: 指名
D71: 新規/顧客/指名 | E71: 0 | F71: 1 | G71: 0 | I71: 新規/顧客/指名 | N71: =E69+E71+J69+J71 -> 0 | O71: =F69+F71+K69+K71 -> 1 | P71: =G69+G71+L69+L71 -> 0
J72: =E68+E70+J68+J70 -> 12000 | K72: =F68+F70+K68+K70 -> 7000 | L72: =SUM(G68+G70+L68+L70+Q68+Q70) -> 5000
A73: 15 | B73: ='【大井町】売上'!C18 -> 日 | C73: 早番 | D73: ='管理シフト'!P49 | E73: 0 | F73: 0 | G73: =E73-F73 -> 0 | I73: ='管理シフト'!S49 | J73: 48000 | K73: 27000 | L73: =J73-K73 -> 21000
D74: 新規/顧客/指名 | I74: 新規/顧客/指名 | J74: 2 | K74: 1 | L74: 0
C75: 遅番 | D75: ='管理シフト'!P50 | E75: 35000 | F75: 15500 | G75: =E75-F75 -> 19500 | I75: ='管理シフト'!S50 | L75: =J75-K75 -> 0 | N75: 新規 | O75: 顧客 | P75: 指名
D76: 新規/顧客/指名 | E76: 1 | F76: 1 | G76: 0 | I76: 新規/顧客/指名 | N76: =E74+E76+J74+J76 -> 3 | O76: =F74+F76+K74+K76 -> 2 | P76: =G74+G76+L74+L76 -> 0
J77: =E73+E75+J73+J75 -> 83000 | K77: =F73+F75+K73+K75 -> 42500 | L77: =SUM(G73+G75+L73+L75+Q73+Q75) -> 40500
A78: 16 | B78: ='【大井町】売上'!C19 -> 月 | C78: 早番 | D78: ='管理シフト'!P52 | G78: =E78-F78 -> 0 | I78: ='管理シフト'!S52 | L78: =J78-K78 -> 0
D79: 新規/顧客/指名 | I79: 新規/顧客/指名
C80: 遅番 | D80: ='管理シフト'!P53 | E80: 73000 | F80: 42000 | G80: =E80-F80 -> 31000 | I80: ='管理シフト'!S53 | L80: =J80-K80 -> 0 | N80: 新規 | O80: 顧客 | P80: 指名
D81: 新規/顧客/指名 | E81: 2 | F81: 2 | G81: 0 | I81: 新規/顧客/指名 | N81: =E79+E81+J79+J81 -> 2 | O81: =F79+F81+K79+K81 -> 2 | P81: =G79+G81+L79+L81 -> 0
J82: =E78+E80+J78+J80 -> 73000 | K82: =F78+F80+K78+K80 -> 42000 | L82: =SUM(G78+G80+L78+L80+Q78+Q80) -> 31000
A83: 17 | B83: ='【大井町】売上'!C20 -> 火 | C83: 早番 | D83: ='管理シフト'!P55 | E83: 0 | F83: 0 | G83: =E83-F83 -> 0 | I83: ='管理シフト'!S55 | J83: 28000 | K83: 17000 | L83: =J83-K83 -> 11000
D84: 新規/顧客/指名 | I84: 新規/顧客/指名 | J84: 1 | K84: 1 | L84: 0
C85: 遅番 | D85: ='管理シフト'!P56 | G85: =E85-F85 -> 0 | I85: ='管理シフト'!S56 | L85: =J85-K85 -> 0 | N85: 新規 | O85: 顧客 | P85: 指名
D86: 新規/顧客/指名 | I86: 新規/顧客/指名 | N86: =E84+E86+J84+J86 -> 1 | O86: =F84+F86+K84+K86 -> 1 | P86: =G84+G86+L84+L86 -> 0
J87: =E83+E85+J83+J85 -> 28000 | K87: =F83+F85+K83+K85 -> 17000 | L87: =SUM(G83+G85+L83+L85+Q83+Q85) -> 11000
A88: 18 | B88: ='【大井町】売上'!C21 -> 水 | C88: 早番 | D88: ='管理シフト'!P58 | E88: 18000 | F88: 10500 | G88: =E88-F88 -> 7500 | I88: ='管理シフト'!S58 | J88: 41000 | K88: 24000 | L88: =J88-K88 -> 17000
D89: 新規/顧客/指名 | E89: 0 | F89: 1 | G89: 0 | I89: 新規/顧客/指名 | J89: 0 | K89: 1 | L89: 1
C90: 遅番 | D90: ='管理シフト'!P59 | G90: =E90-F90 -> 0 | I90: ='管理シフト'!S59 | L90: =J90-K90 -> 0 | N90: 新規 | O90: 顧客 | P90: 指名
D91: 新規/顧客/指名 | I91: 新規/顧客/指名 | N91: =E89+E91+J89+J91 -> 0 | O91: =F89+F91+K89+K91 -> 2 | P91: =G89+G91+L89+L91 -> 1
J92: =E88+E90+J88+J90 -> 59000 | K92: =F88+F90+K88+K90 -> 34500 | L92: =SUM(G88+G90+L88+L90+Q88+Q90) -> 24500
A93: 19 | B93: ='【大井町】売上'!C22 -> 木 | C93: 早番 | D93: ='管理シフト'!P61 | G93: =E93-F93 -> 0 | I93: ='管理シフト'!S61 | J93: 15000 | K93: 8500 | L93: =J93-K93 -> 6500
D94: 新規/顧客/指名 | I94: 新規/顧客/指名 | J94: 0 | K94: 1 | L94: 0
C95: 遅番 | D95: ='管理シフト'!P62 | E95: 32000 | F95: 20000 | G95: =E95-F95 -> 12000 | I95: ='管理シフト'!S62 | L95: =J95-K95 -> 0 | N95: 新規 | O95: 顧客 | P95: 指名
D96: 新規/顧客/指名 | E96: 0 | F96: 2 | G96: 0 | I96: 新規/顧客/指名 | N96: =E94+E96+J94+J96 -> 0 | O96: =F94+F96+K94+K96 -> 3 | P96: =G94+G96+L94+L96 -> 0
J97: =E93+E95+J93+J95 -> 47000 | K97: =F93+F95+K93+K95 -> 28500 | L97: =SUM(G93+G95+L93+L95+Q93+Q95) -> 18500
A98: 20 | B98: ='【大井町】売上'!C23 -> 金 | C98: 早番 | D98: ='管理シフト'!P64 | G98: =E98-F98 -> 0 | I98: ='管理シフト'!S64 | L98: =J98-K98 -> 0
D99: 新規/顧客/指名 | I99: 新規/顧客/指名
C100: 遅番 | D100: ='管理シフト'!P65 | E100: 25000 | F100: 13670 | G100: =E100-F100 -> 11330 | I100: ='管理シフト'!S65 | J100: 20000 | K100: 14000 | L100: =J100-K100 -> 6000 | N100: 新規 | O100: 顧客 | P100: 指名
...

Sheet 管理シフト
G1: スパ・ラウンジ大井町 | J1: ザ・リッツ蒲田
A2: 日付 | B2: 曜日 | C2: 早・遅 | D2: エステムプラザ５０１ | G2: スカイコート８０６ | J2: エルドゥーチェ３０３ | M2: レジディア１００１ | P2: XEBEC巣鴨203 | S2: メインステージ巣鴨404
A3: 31 | B3: 月 | C3: 早番
C4: 遅番
A6: 1 | B6: 日 | C6: 早番 | D6: えみり | E6: １１−１８ | G6: みこ | H6: １１−１７ | J6: やすの | K6: １１−１８ | M6: まな | N6: １２−２２ | S6: てるみ | T6: １２−２０
C7: 遅番 | D7: しおん | E7: １９−２８ | G7: あんず | H7: １８−２３ | J7: ののは | K7: １９−２８ | S7: ののはダミー
A9: 2 | B9: 月 | C9: 早番 | D9: ゆかり | E9: １１−１８ | G9: かずは | H9: １３－１８ | M9: ちひろ | N9: １１.５−１７ | S9: 南さなダミー
C10: 遅番 | D10: えみり | E10: １９−２８ | G10: すみれ | H10: １９−２８ | J10: しおん | K10: １３−２８ | M10: えりか | N10: ２１−２８
A12: 3 | B12: 火 | C12: 早番 | G12: ひより | H12: １２−１７ | J12: ますみ | K12: １１−１７ | M12: てるみ | N12: １２−２２ | P12: ゆかり | Q12: １１−１８
C13: 遅番 | D13: しのぶ | E13: １３−２６ | J13: すみれ | K13: １９−２８ | P13: わかダミー | S13: ほのか | T13: ２０－２７
A15: 4 | B15: 水 | C15: 早番 | G15: てるみ | H15: １２−２０ | J15: ゆかり | K15: １１−１８ | M15: くれは | N15: １３−２２ | P15: まな | Q15: １２－２１ | S15: さな南ダミー
C16: 遅番 | D16: かすみ | E16: １９−２８ | G16: えりか | H16: ２１−２８ | J16: えみり | K16: １９−２８
A18: 5 | B18: 木 | C18: 早番 | D18: ますみ | E18: １１−１７ | J18: てるみ | K18: １２−２２ | M18: ちひろ | N18: １１.５−１７ | P18: あかりダミー
C19: 遅番 | D19: ののは | E19: １８－２８ | G19: しおん | H19: １３−２８ | M19: かずは | N19: １９−２６ | P19: しずか | Q19: １８−２８
A21: 6 | B21: 金 | C21: 早番 | G21: ちなつ | H21: １１－１８ | J21: まな | K21: １２−２０ | M21: ちひろ | N21: １１.５−１７
C22: 遅番 | D22: しずか | E22: １８−２８ | G22: すみれ | H22: １９−２８ | J22: えりか | K22: ２１−２８ | M22: しのぶ | N22: １８−２６ | P22: ほのか | Q22: １１−２７ | S22: ちあき | T22: １６−２６
A24: 7 | B24: 土 | C24: 早番 | D24: ゆかり | E24: １１−１８ | G24: くれは | H24: １３−２２ | J24: てるみ | K24: １２−２２ | M24: くみ | N24: １２−１８ | P24: まな | Q24: １２−２１.５ | S24: かずは | T24: １１−１５.５
C25: 遅番 | D25: わか | E25: １９−２５ | M25: かすみ | N25: １９−２８ | S25: ゆい | T25: １８−２８
A27: 8 | B27: 日 | C27: 早番 | M27: ひより | N27: １２−１７ | S27: てるみ | T27: １２−２０
C28: 遅番 | D28: ののは | E28: １８－２８ | G28: しおん | H28: １３−２８ | J28: わか | K28: １３−２５
A30: 9 | B30: 月 | C30: 早番 | D30: ひより | E30: １２−１７ | G30: かずは | H30: １３−２２ | J30: ゆかり | K30: １１−１８ | M30: ちひろ | N30: １１.５−１７
C31: 遅番 | D31: かすみ | E31: １９−２８ | J31: みこ | K31: １９－２３ | M31: しおん | N31: １８−２８
A33: 10 | B33: 火 | C33: 早番 | D33: てるみ | E33: １２−２２ | J33: えみり | K33: １１−１８ | M33: ひより | N33: １２−１７ | P33: まな | Q33: １２−２１.５
C34: 遅番 | G34: しのぶ | H34: １３−２６ | M34: しずか | N34: １８−２８ | S34: かずは | T34: ２０−２６
A36: 11 | B36: 水 | C36: 早番
C37: 遅番
A39: 12 | B39: 木 | C39: 早番
C40: 遅番
A42: 13 | B42: 金 | C42: 早番
C43: 遅番
A45: 14 | B45: 土 | C45: 早番
C46: 遅番
A49: 15 | B49: 日 | C49: 早番
C50: 遅番
A52: 16 | B52: 月 | C52: 早番
C53: 遅番
A55: 17 | B55: 火 | C55: 早番
C56: 遅番
A58: 18 | B58: 水 | C58: 早番
C59: 遅番
A61: 19 | B61: 木 | C61: 早番
C62: 遅番
A64: 20 | B64: 金 | C64: 早番
C65: 遅番
A67: 21 | B67: 土 | C67: 早番
C68: 遅番
A70: 22 | B70: 日 | C70: 早番
C71: 遅番
A73: 23 | B73: 月 | C73: 早番
C74: 遅番
A76: 24 | B76: 火 | C76: 早番
C77: 遅番
A79: 25 | B79: 水 | C79: 早番
C80: 遅番
A82: 26 | B82: 木 | C82: 早番
C83: 遅番
A85: 27 | B85: 金 | C85: 早番
C86: 遅番
A88: 28 | B88: 土 | C88: 早番
C89: 遅番
B101: ='【大井町】売上'!C42
B104: ='【大井町】売上'!C43
B107: ='【大井町】売上'!C44

Sheet 個人情報
C3: セラピスト名 | H3: ランク | I3: インターバル
I4: X
C5: 店舗 | D5: 契約書 | E5: 部屋 | F5: 期日 | G5: 売上
C6: レギュラー
B7: 1 | C7: あさみ | H7: B | K7: 5店舗掛け持ち。掃除洗濯備品買い出し〇
B8: 2 | C8: くみ | H8: C | K8: 掃除洗濯備品買い出し〇。本職あり 新人の後は入れない
B9: 3 | C9: 南 | G9: SMS | H9: B | K9: ルーム指定あり大井町スカイコートのみ。蒲田エルドゥーチェのみ。アスペルガー。方向音痴。本職あり
B10: 4 | C10: ちなつ | H10: C | I10: NG | K10: 掃除洗濯備品買い出し〇 現役針灸師。）
B11: 5 | C11: 彩華 | H11: B | K11: 5店舗掛け持ち。洗濯掃除備品買い出し〇 スカイコート、レジディア優先
B12: 6 | C12: 春 | H12: C | K12: 気が強いから注意。大井町リフレシュ掛け持ち。洗濯△備品買い出し〇。
B13: 7 | C13: しのぶ | H13: B | K13: スカイコート1205NG、彩華の後はなし、
B14: 8 | C14: わか | H14: C | K14: 5店舗掛け持ち。洗濯△掃除備品買い出し〇
B15: 9 | C15: しおん | H15: A
B16: 10 | C16: みこ | H16: C | I16: B | K16: 彼氏の都合で休みがち
B17: 11 | C17: ゆい | H17: B | I17: B
B18: 12 | C18: まや | H18: B | K18: エステ経験１７年、メンズエステ８年
B19: 13 | C19: みち | H19: B | K19: 5店舗掛け持ち。洗濯掃除備品買い出し〇
B20: 14 | C20: みい | H20: B | K20: 土井さんグループと掛け持ち 大井町のみ 話通じない
B21: 15 | C21: にな | H21: A | K21: 蒲田のみ、休みがち
B22: 16 | C22: ゆあ | H22: A | K22: 5月中旬以降に海外旅行２週間程度
B23: 17 | C23: ちひろ | H23: B | K23: 蒲田のみ
B24: 18 | C24: ゆめ | H24: B | K24: 大井町優先
B25: 19 | C25: みゆか | H25: B | K25: 蒲田希望
B26: 20 | C26: ゆうな | H26: B | K26: 掃除問題あり
B27: 21 | C27: あいり | K27: 大井町のみ(エステムプラザ優先）
B28: 22 | C28: ゆりこ | K28: ワンルーム初めて
B29: 23 | C29: さき
B30: 24 | C30: かほ | K30: 蒲田優先
B31: 25 | C31: かえで | H31: B | K31: 蒲田
B32: 26 | C32: さな
B33: 27 | C33: あまね | H33: B | K33: 方向音痴
B34: 28 | C34: りお | K34: 出稼ぎ | P34: 1
B35: 29 | C35: まなみ | P35: 1
B36: 30 | C36: ますみ | P36: 1
B37: 31 | C37: さくらこ
P40: 1
C41: 準レギュラー | G41: 月1回程度 | P41: 1
B42: 2 | C42: ここあ | K42: 洗濯掃除できない（3回注意済）横浜接骨院勤務、巣鴨リスボアたまに出勤。愛が無い施術, 自己中,
B43: 3 | C43: あさひ | H43: B | K43: 復帰,大井町のみ、リフレシュ掛け持ち
B44: 4 | C44: もみじ | H44: C | K44: 未経験、土曜日のみ12-21
B45: 5 | C45: なつみ | H45: B | K45: 看護士。蒲田在住。（あきさん崇拝者まだつながってます）
B46: 6 | C46: はるみ | I46: 20 | K46: 既婚者１歳の子持ち。11-15
B47: 7 | C47: ひびき | H47: B
B48: 8 | C48: なな | H48: B | K48: 福岡から出張の際に勤務
B49: 9 | C49: さくら | H49: B
B50: 10 | C50: あみ | H50: B
B51: 12 | C51: つきみ | H51: B
B52: 13 | C52: ゆうか | H52: B
B53: 14 | C53: りな | H53: A
C56: 退店・３ヶ月以上連絡なし
B57: 1 | C57: あん | G57: 休 | H57: B | K57: 連絡取れず（4/25現在）本職あり。骨折中
B58: 14 | C58: あすか | G58: 4/25退店 | H58: A | K58: 蒲田店のみ、指圧の学校夕方～。12-16
B59: 16 | C59: かおり | G59: 4/29退店 | H59: A
B60: 18 | C60: うた | G60: 4/25退店 | H60: B＋ | K60: 指圧プロ
B61: 22 | C61: まりな | G61: 4/26退店 | K61: 未経験
B62: 19 | C62: ゆき | G62: 4/30退店 | H62: A | K62: 現役エステシャン、蒲田店のみ
B63: 13 | C63: れい | G63: 退店4/30) | H63: A | K63: 大井町のみ。11-17
B64: 18 | C64: みさき | G64: 5/15退店 | H64: B＋ | K64: ワンルーム怖い
B65: 20 | C65: すず | G65: 5/22退店 | K65: メンヘラ
B66: 18 | C66: かえで | H66: B+
C67: かな | G67: 9/30退店 | H67: B
C68: みう | H68: A
B69: 15 | C69: りか | H69: B
C70: ゆら
B71: 23 | C71: れいな | H71: A
B72: 15 | C72: しず | H72: A
B73: 16 | C73: なの | H73: B | K73: 大井町のみ。土曜＆平日出勤。本職あり。
B74: 13 | C74: りこ | H74: B | K74: 大井町のみ
B75: 10 | C75: ありさ | H75: B | K75: 蒲田のみ。１１ー１４時半まで
B76: 15 | C76: こころ | H76: A | I76: B | K76: 家族の事情で休みがち
B77: 18 | C77: もも | H77: A | K77: 元吉原風俗嬢
B78: 14 | C78: めい | H78: B | I78: NG | K78: 29歳 マッサージうまい

Sheet セラピスト巣鴨PS管理
B2: 巣鴨XEBEC203号室 | E2: エルドゥーチェ303(蒲田) | H2: 共通
C3: パスワード
B4: ゆかり | C4: 642004 | E4: ちなつ | F4: 860673 | H4: A | I4: 533016 | J4: 蒲田あんず | K4: 巣鴨しのぶ
B5: ゆず | C5: 536771 | E5: 春 | F5: 574649 | H5: B | I5: 310258 | J5: 蒲田ひより | K5: 巣鴨まりえ
B6: まな | C6: 349021 | E6: しのぶ | F6: 718868 | H6: C | I6: 833287 | J6: 蒲田なずな | K6: 巣鴨蒲田てるみ
B7: ほのか | C7: 832355 | E7: しずか | F7: 635544 | H7: Ｄ | I7: 289494 | J7: 蒲田つぼみ | K7: 巣鴨やすの
B8: 彩華 | C8: 182226 | E8: なつめ | F8: 863546 | H8: E | I8: 821274 | J8: 蒲田巣鴨ののは
B9: みこ | C9: 185118 | E9: みい | F9: 307942 | H9: F | I9: 194525 | J9: 蒲田巣鴨くれは
B10: わか | C10: 364458 | E10: あゆむ | F10: 0.11436 | H10: G | I10: 486287 | J10: 蒲田巣鴨つむぎ
B11: あさみ | C11: 993773 | E11: ちひろ | F11: 441110 | H11: H | I11: 79332
B12: ゆい | C12: 544084 | E12: えみり | F12: 930336
B13: 南 | C13: 885634 | E13: ここ | F13: 984061
B14: さな | C14: 328237 | E14: えりか | F14: 183954
B15: しおん | C15: 608858 | E15: かりな | F15: 262768
B16: ゆりこ | C16: 853593 | E16: ますみ | F16: 190077
B17: りん | C17: 140928 | E17: かすみ | F17: 765827
B18: 春 | C18: 175984 | E18: くみ | F18: 497652
B19: すみれ | C19: 562243 | E19: もみじ | F19: 198592
B20: いおり | C20: 162549 | E20: ことね | F20: 684275
B21: しずか | C21: 635544 | E21: れみ | F21: 227562
B22: かりな | C22: 318886 | E22: しおん | F22: 608858
B23: れみ | C23: 227562 | E23: まな | F23: 349021
... B29: つぼみ | C29: 289494 | E29: わか | F29: 364458
E30: 南 | F30: 885634
B31: まどか | E31: ゆかり | F31: 642004
E32: かずは | F32: 373322
E33: まどか | F33: 840622
E34: なぎさ | F34: 448330
B35: 新人(A) | C35: 534337 | E35: しょうこ | F35: 853593
B36: 新人(B) | C36: 581270 | E36: つぼみ | F36: 289494
B37: 緊急 | C37: 0.59369 | E37: しずか
B38: 新人C | C38: 0.01576
B41: 使用❌ | C41: 645556

Sheet 物件情報
B5: マンション名 | D5: 住所 | G5: 電気 | H5: ガス | I5: 水道 | J5: Wi-Fi
B6: スカイコート品川仙台坂 806 | D6: 〒140-0011 東京都品川区東大井５丁目26-23 | I6: アプリ登録済み
I7: 11/19クレジット申請
B9: エステムプラザ品川アーバンヒルズ 501 | D9: 〒140-0014 東京都品川区大井１丁目４２−７ | I9: アプリ登録済み
I10: 11/19クレジット申請
B12: レジディア蒲田Ⅱ1001 | D12: 〒144-0052 東京都大田区蒲田５丁目４５−１１
B15: エル・ドゥーチェ蒲田 303 | D15: 〒144-0052 東京都大田区蒲田５丁目４８−５
B18: XEBEC巣鴨203 | D18: 〒170-0002 | H18: クレジット支払い | I18: アプリ登録済み
D19: 東京都豊島区巣鴨1丁目10-9 | H19: 11/19登録 | I19: 11/19クレジット申請
B21: メインステージ巣鴨404 | D21: 〒170-0002 | I21: けんた登録済み？
D22: 東京都豊島区巣鴨2丁目16-3
